[
    {
        "Date": "2025-04-03",
        "Time": "End of Day",
        "Ticker": "BANKINDIA",
        "High_Price": 118.1500015258789,
        "Close_Price": 114.91999816894531,
        "Resistance_Price": 115.0,
        "Distance_to_Resistance": 0.0800018310546875,
        "Volume": 9650.0,
        "Touched_Resistance": "Yes"
    },
    {
        "Date": "2025-04-03",
        "Time": "End of Day",
        "Ticker": "GAIL",
        "High_Price": 185.5,
        "Close_Price": 183.6300048828125,
        "Resistance_Price": 185.0,
        "Distance_to_Resistance": 1.3699951171875,
        "Volume": 20785.0,
        "Touched_Resistance": "Yes"
    }
]