[
    {
        "Ticker": "BANKBARODA",
        "Underlying": 254.53,
        "Option_Type": "CE",
        "Suggested_Sell_Strike": 260.0,
        "Current_Premium": 4.55,
        "Previous_Premium": 2.1,
        "Premium_Change_%": 116.66666666666666,
        "Expiry": "26-Jun-2025",
        "Timestamp": "2025-06-04 21:11:04",
        "Resistance": 261.6666666666667,
        "Support": 250.0
    },
    {
        "Ticker": "BANKBARODA",
        "Underlying": 254.53,
        "Option_Type": "CE",
        "Suggested_Sell_Strike": 265.0,
        "Current_Premium": 2.95,
        "Previous_Premium": 1.35,
        "Premium_Change_%": 118.5185185185185,
        "Expiry": "26-Jun-2025",
        "Timestamp": "2025-06-04 21:11:04",
        "Resistance": 261.6666666666667,
        "Support": 250.0
    },
    {
        "Ticker": "BANKBARODA",
        "Underlying": 254.53,
        "Option_Type": "CE",
        "Suggested_Sell_Strike": 255.0,
        "Current_Premium": 6.8,
        "Previous_Premium": 3.25,
        "Premium_Change_%": 109.23076923076923,
        "Expiry": "26-Jun-2025",
        "Timestamp": "2025-06-04 21:11:04",
        "Resistance": 261.6666666666667,
        "Support": 250.0
    },
    {
        "Ticker": "BANKBARODA",
        "Underlying": 254.53,
        "Option_Type": "CE",
        "Suggested_Sell_Strike": 275.0,
        "Current_Premium": 1.15,
        "Previous_Premium": 0.55,
        "Premium_Change_%": 109.09090909090907,
        "Expiry": "26-Jun-2025",
        "Timestamp": "2025-06-04 21:11:04",
        "Resistance": 261.6666666666667,
        "Support": 250.0
    },
    {
        "Ticker": "CANBK",
        "Underlying": 117.2,
        "Option_Type": "CE",
        "Suggested_Sell_Strike": 118.0,
        "Current_Premium": 3.5,
        "Previous_Premium": 1.6,
        "Premium_Change_%": 118.74999999999997,
        "Expiry": "26-Jun-2025",
        "Timestamp": "2025-06-04 21:11:05",
        "Resistance": 117.66666666666667,
        "Support": 108.33333333333333
    },
    {
        "Ticker": "CANBK",
        "Underlying": 117.2,
        "Option_Type": "CE",
        "Suggested_Sell_Strike": 120.0,
        "Current_Premium": 2.65,
        "Previous_Premium": 1.25,
        "Premium_Change_%": 111.99999999999999,
        "Expiry": "26-Jun-2025",
        "Timestamp": "2025-06-04 21:11:05",
        "Resistance": 117.66666666666667,
        "Support": 108.33333333333333
    },
    {
        "Ticker": "CUMMINSIND",
        "Underlying": 3342,
        "Option_Type": "CE",
        "Suggested_Sell_Strike": 3400.0,
        "Current_Premium": 76.85,
        "Previous_Premium": 22.55,
        "Premium_Change_%": 240.7982261640798,
        "Expiry": "26-Jun-2025",
        "Timestamp": "2025-06-04 21:11:05",
        "Resistance": 3350.0,
        "Support": 3200.0
    },
    {
        "Ticker": "GLENMARK",
        "Underlying": 1518.2,
        "Option_Type": "CE",
        "Suggested_Sell_Strike": 1600.0,
        "Current_Premium": 20.8,
        "Previous_Premium": 4.2,
        "Premium_Change_%": 395.23809523809524,
        "Expiry": "26-Jun-2025",
        "Timestamp": "2025-06-04 21:11:06",
        "Resistance": 1540.0,
        "Support": 1453.3333333333333
    },
    {
        "Ticker": "GLENMARK",
        "Underlying": 1518.2,
        "Option_Type": "CE",
        "Suggested_Sell_Strike": 1640.0,
        "Current_Premium": 12.0,
        "Previous_Premium": 3.1,
        "Premium_Change_%": 287.0967741935484,
        "Expiry": "26-Jun-2025",
        "Timestamp": "2025-06-04 21:11:06",
        "Resistance": 1540.0,
        "Support": 1453.3333333333333
    },
    {
        "Ticker": "MCX",
        "Underlying": 6890,
        "Option_Type": "CE",
        "Suggested_Sell_Strike": 7200.0,
        "Current_Premium": 144.1,
        "Previous_Premium": 67.95,
        "Premium_Change_%": 112.06769683590873,
        "Expiry": "26-Jun-2025",
        "Timestamp": "2025-06-04 21:11:11",
        "Resistance": 7200.0,
        "Support": 6633.333333333333
    },
    {
        "Ticker": "MCX",
        "Underlying": 6890,
        "Option_Type": "CE",
        "Suggested_Sell_Strike": 6900.0,
        "Current_Premium": 270.0,
        "Previous_Premium": 132.95,
        "Premium_Change_%": 103.08386611508087,
        "Expiry": "26-Jun-2025",
        "Timestamp": "2025-06-04 21:11:11",
        "Resistance": 7200.0,
        "Support": 6633.333333333333
    },
    {
        "Ticker": "MCX",
        "Underlying": 6890,
        "Option_Type": "CE",
        "Suggested_Sell_Strike": 7000.0,
        "Current_Premium": 221.0,
        "Previous_Premium": 106.95,
        "Premium_Change_%": 106.63861617578307,
        "Expiry": "26-Jun-2025",
        "Timestamp": "2025-06-04 21:11:11",
        "Resistance": 7200.0,
        "Support": 6633.333333333333
    },
    {
        "Ticker": "MUTHOOTFIN",
        "Underlying": 2270,
        "Option_Type": "CE",
        "Suggested_Sell_Strike": 2440.0,
        "Current_Premium": 13.05,
        "Previous_Premium": 3.2,
        "Premium_Change_%": 307.81250000000006,
        "Expiry": "26-Jun-2025",
        "Timestamp": "2025-06-04 21:11:11",
        "Resistance": 2300.0,
        "Support": 2100.0
    },
    {
        "Ticker": "MUTHOOTFIN",
        "Underlying": 2270,
        "Option_Type": "CE",
        "Suggested_Sell_Strike": 2340.0,
        "Current_Premium": 35.3,
        "Previous_Premium": 11.4,
        "Premium_Change_%": 209.6491228070175,
        "Expiry": "26-Jun-2025",
        "Timestamp": "2025-06-04 21:11:11",
        "Resistance": 2300.0,
        "Support": 2100.0
    },
    {
        "Ticker": "MUTHOOTFIN",
        "Underlying": 2270,
        "Option_Type": "CE",
        "Suggested_Sell_Strike": 2480.0,
        "Current_Premium": 8.85,
        "Previous_Premium": 2.85,
        "Premium_Change_%": 210.52631578947367,
        "Expiry": "26-Jun-2025",
        "Timestamp": "2025-06-04 21:11:11",
        "Resistance": 2300.0,
        "Support": 2100.0
    },
    {
        "Ticker": "MUTHOOTFIN",
        "Underlying": 2270,
        "Option_Type": "CE",
        "Suggested_Sell_Strike": 2280.0,
        "Current_Premium": 61.2,
        "Previous_Premium": 20.55,
        "Premium_Change_%": 197.8102189781022,
        "Expiry": "26-Jun-2025",
        "Timestamp": "2025-06-04 21:11:11",
        "Resistance": 2300.0,
        "Support": 2100.0
    },
    {
        "Ticker": "MUTHOOTFIN",
        "Underlying": 2270,
        "Option_Type": "CE",
        "Suggested_Sell_Strike": 2400.0,
        "Current_Premium": 19.45,
        "Previous_Premium": 6.5,
        "Premium_Change_%": 199.2307692307692,
        "Expiry": "26-Jun-2025",
        "Timestamp": "2025-06-04 21:11:11",
        "Resistance": 2300.0,
        "Support": 2100.0
    },
    {
        "Ticker": "MUTHOOTFIN",
        "Underlying": 2270,
        "Option_Type": "CE",
        "Suggested_Sell_Strike": 2520.0,
        "Current_Premium": 5.7,
        "Previous_Premium": 2.35,
        "Premium_Change_%": 142.5531914893617,
        "Expiry": "26-Jun-2025",
        "Timestamp": "2025-06-04 21:11:11",
        "Resistance": 2300.0,
        "Support": 2100.0
    },
    {
        "Ticker": "MUTHOOTFIN",
        "Underlying": 2270,
        "Option_Type": "CE",
        "Suggested_Sell_Strike": 2300.0,
        "Current_Premium": 51.35,
        "Previous_Premium": 17.3,
        "Premium_Change_%": 196.8208092485549,
        "Expiry": "26-Jun-2025",
        "Timestamp": "2025-06-04 21:11:11",
        "Resistance": 2300.0,
        "Support": 2100.0
    },
    {
        "Ticker": "MUTHOOTFIN",
        "Underlying": 2270,
        "Option_Type": "CE",
        "Suggested_Sell_Strike": 2500.0,
        "Current_Premium": 6.85,
        "Previous_Premium": 2.85,
        "Premium_Change_%": 140.35087719298244,
        "Expiry": "26-Jun-2025",
        "Timestamp": "2025-06-04 21:11:11",
        "Resistance": 2300.0,
        "Support": 2100.0
    },
    {
        "Ticker": "MUTHOOTFIN",
        "Underlying": 2270,
        "Option_Type": "CE",
        "Suggested_Sell_Strike": 2460.0,
        "Current_Premium": 10.5,
        "Previous_Premium": 5.15,
        "Premium_Change_%": 103.88349514563104,
        "Expiry": "26-Jun-2025",
        "Timestamp": "2025-06-04 21:11:11",
        "Resistance": 2300.0,
        "Support": 2100.0
    },
    {
        "Ticker": "MUTHOOTFIN",
        "Underlying": 2270,
        "Option_Type": "CE",
        "Suggested_Sell_Strike": 2320.0,
        "Current_Premium": 43.0,
        "Previous_Premium": 15.0,
        "Premium_Change_%": 186.66666666666666,
        "Expiry": "26-Jun-2025",
        "Timestamp": "2025-06-04 21:11:11",
        "Resistance": 2300.0,
        "Support": 2100.0
    },
    {
        "Ticker": "PNB",
        "Underlying": 109.61,
        "Option_Type": "CE",
        "Suggested_Sell_Strike": 116.0,
        "Current_Premium": 1.35,
        "Previous_Premium": 0.5,
        "Premium_Change_%": 170.00000000000003,
        "Expiry": "26-Jun-2025",
        "Timestamp": "2025-06-04 21:11:12",
        "Resistance": 115.0,
        "Support": 105.0
    },
    {
        "Ticker": "PNB",
        "Underlying": 109.61,
        "Option_Type": "CE",
        "Suggested_Sell_Strike": 114.0,
        "Current_Premium": 1.85,
        "Previous_Premium": 0.7,
        "Premium_Change_%": 164.28571428571433,
        "Expiry": "26-Jun-2025",
        "Timestamp": "2025-06-04 21:11:12",
        "Resistance": 115.0,
        "Support": 105.0
    },
    {
        "Ticker": "PNB",
        "Underlying": 109.61,
        "Option_Type": "CE",
        "Suggested_Sell_Strike": 110.0,
        "Current_Premium": 3.55,
        "Previous_Premium": 1.3,
        "Premium_Change_%": 173.07692307692307,
        "Expiry": "26-Jun-2025",
        "Timestamp": "2025-06-04 21:11:12",
        "Resistance": 115.0,
        "Support": 105.0
    },
    {
        "Ticker": "PNB",
        "Underlying": 109.61,
        "Option_Type": "CE",
        "Suggested_Sell_Strike": 111.0,
        "Current_Premium": 3.05,
        "Previous_Premium": 1.1,
        "Premium_Change_%": 177.27272727272722,
        "Expiry": "26-Jun-2025",
        "Timestamp": "2025-06-04 21:11:12",
        "Resistance": 115.0,
        "Support": 105.0
    },
    {
        "Ticker": "PNB",
        "Underlying": 109.61,
        "Option_Type": "CE",
        "Suggested_Sell_Strike": 112.0,
        "Current_Premium": 2.6,
        "Previous_Premium": 0.9,
        "Premium_Change_%": 188.8888888888889,
        "Expiry": "26-Jun-2025",
        "Timestamp": "2025-06-04 21:11:12",
        "Resistance": 115.0,
        "Support": 105.0
    },
    {
        "Ticker": "SRF",
        "Underlying": 3053.5,
        "Option_Type": "CE",
        "Suggested_Sell_Strike": 3100.0,
        "Current_Premium": 62.4,
        "Previous_Premium": 30.65,
        "Premium_Change_%": 103.58890701468191,
        "Expiry": "26-Jun-2025",
        "Timestamp": "2025-06-04 21:11:12",
        "Resistance": 3100.0,
        "Support": 2900.0
    },
    {
        "Ticker": "SRF",
        "Underlying": 3053.5,
        "Option_Type": "CE",
        "Suggested_Sell_Strike": 3150.0,
        "Current_Premium": 44.45,
        "Previous_Premium": 22.0,
        "Premium_Change_%": 102.04545454545455,
        "Expiry": "26-Jun-2025",
        "Timestamp": "2025-06-04 21:11:12",
        "Resistance": 3100.0,
        "Support": 2900.0
    },
    {
        "Ticker": "FEDERALBNK",
        "Underlying": 210.9,
        "Option_Type": "CE",
        "Suggested_Sell_Strike": 225.0,
        "Current_Premium": 1.05,
        "Previous_Premium": 0.45,
        "Premium_Change_%": 133.33333333333334,
        "Expiry": "26-Jun-2025",
        "Timestamp": "2025-06-04 21:11:14",
        "Resistance": 215.0,
        "Support": 205.0
    },
    {
        "Ticker": "FEDERALBNK",
        "Underlying": 210.9,
        "Option_Type": "CE",
        "Suggested_Sell_Strike": 230.0,
        "Current_Premium": 0.6,
        "Previous_Premium": 0.3,
        "Premium_Change_%": 100.0,
        "Expiry": "26-Jun-2025",
        "Timestamp": "2025-06-04 21:11:14",
        "Resistance": 215.0,
        "Support": 205.0
    },
    {
        "Ticker": "FEDERALBNK",
        "Underlying": 210.9,
        "Option_Type": "CE",
        "Suggested_Sell_Strike": 220.0,
        "Current_Premium": 1.9,
        "Previous_Premium": 0.9,
        "Premium_Change_%": 111.1111111111111,
        "Expiry": "26-Jun-2025",
        "Timestamp": "2025-06-04 21:11:14",
        "Resistance": 215.0,
        "Support": 205.0
    },
    {
        "Ticker": "FEDERALBNK",
        "Underlying": 210.9,
        "Option_Type": "CE",
        "Suggested_Sell_Strike": 215.0,
        "Current_Premium": 3.35,
        "Previous_Premium": 1.6,
        "Premium_Change_%": 109.375,
        "Expiry": "26-Jun-2025",
        "Timestamp": "2025-06-04 21:11:14",
        "Resistance": 215.0,
        "Support": 205.0
    },
    {
        "Ticker": "UNIONBANK",
        "Underlying": 153.78,
        "Option_Type": "CE",
        "Suggested_Sell_Strike": 155.0,
        "Current_Premium": 5.1,
        "Previous_Premium": 2.15,
        "Premium_Change_%": 137.2093023255814,
        "Expiry": "26-Jun-2025",
        "Timestamp": "2025-06-04 21:11:14",
        "Resistance": 155.0,
        "Support": 145.0
    }
]