[
  {
    "Ticker": "AUBANK",
    "Today_Close": 959.65,
    "Surge_High": 1079.55,
    "Yesterday_High": 1013.3,
    "Yesterday_Close": 984.7,
    "Yesterday_Low": 971.1,
    "Drop_Pct": 0.2,
    "Breakdown_Volume": 1546836,
    "Avg_Volume_20d": 1645736,
    "Volume_Ratio": 0.94,
    "EMA_At_Detection": 989.23,
    "EMA_Breached_At_Detection": true,
    "Below_EMA": true,
    "Surge_Gain_Pct": 26.46,
    "Surge_Candles": 13,
    "Surge_Allowed_Reds": 4,
    "Surge_Start": "2026-03-30",
    "Surge_End": "2026-04-24",
    "Days_Since_Surge_End": 40,
    "Prev_Pullup_High": 1079.55,
    "Lifetime_52W_High": 1079.55,
    "Suggested_Strike": 1100.0,
    "Expiry": "30-Jun-2026",
    "CE_LTP": 2.65,
    "CE_OI": 518,
    "IV_Pct": 32.3,
    "CE_30d_High": 28.25,
    "CE_Above_30d_High": false,
    "Remark": "CE Below 30d High",
    "NSE_Hist_Calls": 1,
    "BCS_Hedge_Strike": 1200.0,
    "BCS_Hedge_CE_LTP": 0.5,
    "BCS_Hedge_CE_OI": 53,
    "BCS_Spread_Width": 100.0,
    "BCS_Net_Premium": 2.15,
    "BCS_Max_Profit": 2.15,
    "BCS_Max_Loss": 97.85,
    "BCS_Breakeven": 1102.15,
    "BCS_Risk_Reward": 45.51,
    "Status": "Momentum Lost",
    "Sell_Alert_Sent": false,
    "Breakdown_Date": "2026-06-01",
    "Sell_Zone_EMA_Confirmed": true,
    "Sell_Zone_EMA_Confirm_Date": "2026-05-13",
    "Scanned_At": "2026-06-03 12:51:29"
  },
  {
    "Ticker": "ASHOKLEY",
    "Today_Close": 143.55,
    "Surge_High": 178.35,
    "Yesterday_High": 154.96,
    "Yesterday_Close": 147.27,
    "Yesterday_Low": 146.91,
    "Drop_Pct": 0.25,
    "Breakdown_Volume": 43162735,
    "Avg_Volume_20d": 25371267,
    "Volume_Ratio": 1.7,
    "EMA_At_Detection": 153.05,
    "EMA_Breached_At_Detection": true,
    "Below_EMA": true,
    "Surge_Gain_Pct": 20.57,
    "Surge_Candles": 9,
    "Surge_Allowed_Reds": 4,
    "Surge_Start": "2026-04-02",
    "Surge_End": "2026-04-22",
    "Days_Since_Surge_End": 42,
    "Prev_Pullup_High": 211.81,
    "Lifetime_52W_High": 211.81,
    "Suggested_Strike": 180.0,
    "Expiry": "30-Jun-2026",
    "CE_LTP": 0.35,
    "CE_OI": 2122,
    "IV_Pct": 47.1,
    "CE_30d_High": 5.77,
    "CE_Above_30d_High": false,
    "Remark": "CE Below 30d High",
    "NSE_Hist_Calls": 1,
    "BCS_Hedge_Strike": 190.0,
    "BCS_Hedge_CE_LTP": 0.2,
    "BCS_Hedge_CE_OI": 1232,
    "BCS_Spread_Width": 10.0,
    "BCS_Net_Premium": 0.15,
    "BCS_Max_Profit": 0.15,
    "BCS_Max_Loss": 9.85,
    "BCS_Breakeven": 180.15,
    "BCS_Risk_Reward": 65.67,
    "Status": "Momentum Lost",
    "Sell_Alert_Sent": false,
    "Breakdown_Date": "2026-06-02",
    "Sell_Zone_EMA_Confirmed": true,
    "Sell_Zone_EMA_Confirm_Date": "2026-05-18",
    "Scanned_At": "2026-06-03 12:52:14"
  },
  {
    "Ticker": "ASIANPAINT",
    "Today_Close": 2647.0,
    "Surge_High": 2748.2,
    "Yesterday_High": 2665.7,
    "Yesterday_Close": 2622.2,
    "Yesterday_Low": 2610.0,
    "Drop_Pct": 0.17,
    "Breakdown_Volume": 796240,
    "Avg_Volume_20d": 1084594,
    "Volume_Ratio": 0.73,
    "EMA_At_Detection": 2562.35,
    "EMA_Breached_At_Detection": true,
    "Below_EMA": false,
    "Surge_Gain_Pct": 18.16,
    "Surge_Candles": 10,
    "Surge_Allowed_Reds": 3,
    "Surge_Start": "2026-04-02",
    "Surge_End": "2026-04-22",
    "Days_Since_Surge_End": 34,
    "Prev_Pullup_High": 2734.7,
    "Lifetime_52W_High": 2985.7,
    "Suggested_Strike": 2800,
    "Expiry": "30-Jun-2026",
    "CE_LTP": 117.6,
    "CE_OI": 453,
    "IV_Pct": 25.4,
    "CE_30d_High": 126.75,
    "CE_Above_30d_High": false,
    "Remark": "CE Below 30d High",
    "NSE_Hist_Calls": 1,
    "BCS_Hedge_Strike": 2800.0,
    "BCS_Hedge_CE_LTP": 37.95,
    "BCS_Hedge_CE_OI": 962,
    "BCS_Spread_Width": 200.0,
    "BCS_Net_Premium": 79.65,
    "BCS_Max_Profit": 79.65,
    "BCS_Max_Loss": 120.35,
    "BCS_Breakeven": 2679.65,
    "BCS_Risk_Reward": 1.51,
    "Status": "Momentum Lost",
    "Sell_Alert_Sent": false,
    "Breakdown_Date": "2026-05-15",
    "Sell_Zone_EMA_Confirmed": true,
    "Sell_Zone_EMA_Confirm_Date": "2026-06-01",
    "Scanned_At": "2026-05-26 16:41:21"
  },
  {
    "Ticker": "DMART",
    "Today_Close": 4176.0,
    "Surge_High": 4562.6,
    "Yesterday_High": 4124.4,
    "Yesterday_Close": 4124.4,
    "Yesterday_Low": 4124.4,
    "Drop_Pct": 1.69,
    "Breakdown_Volume": 2177691,
    "Avg_Volume_20d": 316640,
    "Volume_Ratio": 6.88,
    "EMA_At_Detection": 4143.18,
    "EMA_Breached_At_Detection": true,
    "Below_EMA": true,
    "Surge_Gain_Pct": 24.5,
    "Surge_Candles": 7,
    "Surge_Allowed_Reds": 1,
    "Surge_Start": "2026-03-23",
    "Surge_End": "2026-04-06",
    "Days_Since_Surge_End": 58,
    "Prev_Pullup_High": 4644.0,
    "Lifetime_52W_High": 4818.0,
    "Suggested_Strike": 4600.0,
    "Expiry": "30-Jun-2026",
    "CE_LTP": 17.55,
    "CE_OI": 368,
    "IV_Pct": 27.6,
    "CE_30d_High": 91.35,
    "CE_Above_30d_High": false,
    "Remark": "CE Below 30d High",
    "NSE_Hist_Calls": 1,
    "BCS_Hedge_Strike": 4800.0,
    "BCS_Hedge_CE_LTP": 7.55,
    "BCS_Hedge_CE_OI": 207,
    "BCS_Spread_Width": 200.0,
    "BCS_Net_Premium": 10.0,
    "BCS_Max_Profit": 10.0,
    "BCS_Max_Loss": 190.0,
    "BCS_Breakeven": 4610.0,
    "BCS_Risk_Reward": 19.0,
    "Status": "Momentum Lost",
    "Sell_Alert_Sent": false,
    "Breakdown_Date": "2026-05-29",
    "Sell_Zone_EMA_Confirmed": true,
    "Sell_Zone_EMA_Confirm_Date": "2026-05-25",
    "Scanned_At": "2026-06-03 12:52:32"
  },
  {
    "Ticker": "AXISBANK",
    "Today_Close": 1251.6,
    "Surge_High": 1391.0,
    "Yesterday_High": 1293.2,
    "Yesterday_Close": 1275.9,
    "Yesterday_Low": 1267.0,
    "Drop_Pct": 1.25,
    "Breakdown_Volume": 11884695,
    "Avg_Volume_20d": 6411390,
    "Volume_Ratio": 1.85,
    "EMA_At_Detection": 1277.67,
    "EMA_Breached_At_Detection": true,
    "Below_EMA": true,
    "Surge_Gain_Pct": 18.8,
    "Surge_Candles": 10,
    "Surge_Allowed_Reds": 5,
    "Surge_Start": "2026-03-30",
    "Surge_End": "2026-04-22",
    "Days_Since_Surge_End": 42,
    "Prev_Pullup_High": 1418.3,
    "Lifetime_52W_High": 1418.3,
    "Suggested_Strike": 1400.0,
    "Expiry": "30-Jun-2026",
    "CE_LTP": 2.5,
    "CE_OI": 3165,
    "IV_Pct": 25.7,
    "CE_30d_High": 48.0,
    "CE_Above_30d_High": false,
    "Remark": "CE Below 30d High",
    "NSE_Hist_Calls": 1,
    "BCS_Hedge_Strike": 1500.0,
    "BCS_Hedge_CE_LTP": 0.35,
    "BCS_Hedge_CE_OI": 39,
    "BCS_Spread_Width": 100.0,
    "BCS_Net_Premium": 2.15,
    "BCS_Max_Profit": 2.15,
    "BCS_Max_Loss": 97.85,
    "BCS_Breakeven": 1402.15,
    "BCS_Risk_Reward": 45.51,
    "Status": "Momentum Lost",
    "Sell_Alert_Sent": false,
    "Breakdown_Date": "2026-06-02",
    "Sell_Zone_EMA_Confirmed": true,
    "Sell_Zone_EMA_Confirm_Date": "2026-05-18",
    "Scanned_At": "2026-06-03 12:52:46"
  },
  {
    "Ticker": "BANDHANBNK",
    "Today_Close": 204.3,
    "Surge_High": 212.66,
    "Yesterday_High": 203.8,
    "Yesterday_Close": 196.07,
    "Yesterday_Low": 195.46,
    "Drop_Pct": 0.3,
    "Breakdown_Volume": 11577289,
    "Avg_Volume_20d": 17756737,
    "Volume_Ratio": 0.65,
    "EMA_At_Detection": 198.78,
    "EMA_Breached_At_Detection": true,
    "Below_EMA": true,
    "Surge_Gain_Pct": 47.78,
    "Surge_Candles": 18,
    "Surge_Allowed_Reds": 7,
    "Surge_Start": "2026-03-30",
    "Surge_End": "2026-05-06",
    "Days_Since_Surge_End": 28,
    "Prev_Pullup_High": 212.66,
    "Lifetime_52W_High": 212.66,
    "Suggested_Strike": 215.0,
    "Expiry": "30-Jun-2026",
    "CE_LTP": 4.4,
    "CE_OI": 663,
    "IV_Pct": 36.9,
    "CE_30d_High": 11.14,
    "CE_Above_30d_High": false,
    "Remark": "CE Below 30d High",
    "NSE_Hist_Calls": 1,
    "BCS_Hedge_Strike": 225.0,
    "BCS_Hedge_CE_LTP": 2.13,
    "BCS_Hedge_CE_OI": 601,
    "BCS_Spread_Width": 10.0,
    "BCS_Net_Premium": 2.27,
    "BCS_Max_Profit": 2.27,
    "BCS_Max_Loss": 7.73,
    "BCS_Breakeven": 217.27,
    "BCS_Risk_Reward": 3.41,
    "Status": "Momentum Lost",
    "Sell_Alert_Sent": false,
    "Breakdown_Date": "2026-05-13",
    "Sell_Zone_EMA_Confirmed": true,
    "Sell_Zone_EMA_Confirm_Date": "2026-05-13",
    "Scanned_At": "2026-06-03 12:53:22"
  },
  {
    "Ticker": "BHARATFORG",
    "Today_Close": 1930.4,
    "Surge_High": 2044.0,
    "Yesterday_High": 1910.0,
    "Yesterday_Close": 1891.0,
    "Yesterday_Low": 1865.4,
    "Drop_Pct": 0.43,
    "Breakdown_Volume": 1020594,
    "Avg_Volume_20d": 1469283,
    "Volume_Ratio": 0.69,
    "EMA_At_Detection": 1908.87,
    "EMA_Breached_At_Detection": true,
    "Below_EMA": true,
    "Surge_Gain_Pct": 18.6,
    "Surge_Candles": 10,
    "Surge_Allowed_Reds": 3,
    "Surge_Start": "2026-02-10",
    "Surge_End": "2026-02-26",
    "Days_Since_Surge_End": 89,
    "Prev_Pullup_High": 1949.9,
    "Lifetime_52W_High": 2044.0,
    "Suggested_Strike": 2100,
    "Expiry": "30-Jun-2026",
    "CE_LTP": 87.85,
    "CE_OI": 63,
    "IV_Pct": 32.1,
    "CE_30d_High": 78.75,
    "CE_Above_30d_High": true,
    "Remark": "CE at New High",
    "NSE_Hist_Calls": 1,
    "BCS_Hedge_Strike": 2020.0,
    "BCS_Hedge_CE_LTP": 38.8,
    "BCS_Hedge_CE_OI": 51,
    "BCS_Spread_Width": 100.0,
    "BCS_Net_Premium": 49.05,
    "BCS_Max_Profit": 49.05,
    "BCS_Max_Loss": 50.95,
    "BCS_Breakeven": 1969.05,
    "BCS_Risk_Reward": 1.04,
    "Status": "Momentum Lost",
    "Sell_Alert_Sent": false,
    "Breakdown_Date": "2026-05-19",
    "Sell_Zone_EMA_Confirmed": true,
    "Sell_Zone_EMA_Confirm_Date": "2026-05-19",
    "Scanned_At": "2026-05-26 16:43:00"
  },
  {
    "Ticker": "BOSCHLTD",
    "Today_Close": 37375.0,
    "Surge_High": 37670.0,
    "Yesterday_High": 36760.0,
    "Yesterday_Close": 36310.0,
    "Yesterday_Low": 36200.0,
    "Drop_Pct": 1.01,
    "Breakdown_Volume": 21187,
    "Avg_Volume_20d": 34689,
    "Volume_Ratio": 0.61,
    "EMA_At_Detection": 36364.16,
    "EMA_Breached_At_Detection": true,
    "Below_EMA": true,
    "Surge_Gain_Pct": 29.87,
    "Surge_Candles": 7,
    "Surge_Allowed_Reds": 1,
    "Surge_Start": "2026-03-30",
    "Surge_End": "2026-04-10",
    "Days_Since_Surge_End": 54,
    "Prev_Pullup_High": 38855.0,
    "Lifetime_52W_High": 40190.0,
    "Suggested_Strike": 37750.0,
    "Expiry": "30-Jun-2026",
    "CE_LTP": 1140.05,
    "CE_OI": 132,
    "IV_Pct": 30.4,
    "CE_30d_High": 2103.1,
    "CE_Above_30d_High": false,
    "Remark": "CE Below 30d High",
    "NSE_Hist_Calls": 1,
    "BCS_Hedge_Strike": 38250.0,
    "BCS_Hedge_CE_LTP": 900.0,
    "BCS_Hedge_CE_OI": 44,
    "BCS_Spread_Width": 500.0,
    "BCS_Net_Premium": 240.05,
    "BCS_Max_Profit": 240.05,
    "BCS_Max_Loss": 259.95,
    "BCS_Breakeven": 37990.05,
    "BCS_Risk_Reward": 1.08,
    "Status": "Momentum Lost",
    "Sell_Alert_Sent": false,
    "Breakdown_Date": "2026-05-26",
    "Sell_Zone_EMA_Confirmed": true,
    "Sell_Zone_EMA_Confirm_Date": "2026-05-26",
    "Scanned_At": "2026-06-03 12:54:10"
  },
  {
    "Ticker": "CDSL",
    "Today_Close": 1209.5,
    "Surge_High": 1399.9,
    "Yesterday_High": 1269.3,
    "Yesterday_Close": 1244.6,
    "Yesterday_Low": 1236.1,
    "Drop_Pct": 1.7,
    "Breakdown_Volume": 1377240,
    "Avg_Volume_20d": 2151610,
    "Volume_Ratio": 0.64,
    "EMA_At_Detection": 1226.27,
    "EMA_Breached_At_Detection": true,
    "Below_EMA": true,
    "Surge_Gain_Pct": 24.46,
    "Surge_Candles": 10,
    "Surge_Allowed_Reds": 2,
    "Surge_Start": "2026-03-30",
    "Surge_End": "2026-04-17",
    "Days_Since_Surge_End": 47,
    "Prev_Pullup_High": 1412.0,
    "Lifetime_52W_High": 1673.7,
    "Suggested_Strike": 1400.0,
    "Expiry": "30-Jun-2026",
    "CE_LTP": 4.4,
    "CE_OI": 2790,
    "IV_Pct": 36.4,
    "CE_30d_High": 26.65,
    "CE_Above_30d_High": false,
    "Remark": "CE Below 30d High",
    "NSE_Hist_Calls": 1,
    "BCS_Hedge_Strike": null,
    "BCS_Hedge_CE_LTP": null,
    "BCS_Hedge_CE_OI": null,
    "BCS_Spread_Width": null,
    "BCS_Net_Premium": null,
    "BCS_Max_Profit": null,
    "BCS_Max_Loss": null,
    "BCS_Breakeven": null,
    "BCS_Risk_Reward": null,
    "Status": "Momentum Lost",
    "Sell_Alert_Sent": false,
    "Breakdown_Date": "2026-06-01",
    "Sell_Zone_EMA_Confirmed": true,
    "Sell_Zone_EMA_Confirm_Date": "2026-05-12",
    "Scanned_At": "2026-06-03 12:54:34"
  },
  {
    "Ticker": "COFORGE",
    "Today_Close": 1430.1,
    "Surge_High": 1387.8,
    "Yesterday_High": 1554.0,
    "Yesterday_Close": 1519.5,
    "Yesterday_Low": 1462.0,
    "Drop_Pct": 2.18,
    "Breakdown_Volume": 3475672,
    "Avg_Volume_20d": 5384989,
    "Volume_Ratio": 0.65,
    "EMA_At_Detection": 1426.78,
    "EMA_Breached_At_Detection": true,
    "Below_EMA": false,
    "Surge_Gain_Pct": 19.42,
    "Surge_Candles": 3,
    "Surge_Allowed_Reds": 3,
    "Surge_Start": "2026-05-04",
    "Surge_End": "2026-05-11",
    "Days_Since_Surge_End": 23,
    "Prev_Pullup_High": 1759.0,
    "Lifetime_52W_High": 1984.96,
    "Suggested_Strike": 1400.0,
    "Expiry": "30-Jun-2026",
    "CE_LTP": 66.1,
    "CE_OI": 2563,
    "IV_Pct": 29.6,
    "CE_30d_High": 128.1,
    "CE_Above_30d_High": false,
    "Remark": "CE Below 30d High",
    "NSE_Hist_Calls": 1,
    "BCS_Hedge_Strike": 1500.0,
    "BCS_Hedge_CE_LTP": 27.85,
    "BCS_Hedge_CE_OI": 2685,
    "BCS_Spread_Width": 100.0,
    "BCS_Net_Premium": 38.25,
    "BCS_Max_Profit": 38.25,
    "BCS_Max_Loss": 61.75,
    "BCS_Breakeven": 1438.25,
    "BCS_Risk_Reward": 1.61,
    "Status": "Momentum Lost",
    "Sell_Alert_Sent": false,
    "Breakdown_Date": "2026-06-03",
    "Sell_Zone_EMA_Confirmed": true,
    "Sell_Zone_EMA_Confirm_Date": "2026-05-14",
    "Scanned_At": "2026-06-03 12:54:56"
  },
  {
    "Ticker": "COLPAL",
    "Today_Close": 2013.6,
    "Surge_High": 2152.43,
    "Yesterday_High": 2084.33,
    "Yesterday_Close": 2035.9,
    "Yesterday_Low": 2026.51,
    "Drop_Pct": 1.8,
    "Breakdown_Volume": 689578,
    "Avg_Volume_20d": 416757,
    "Volume_Ratio": 1.65,
    "EMA_At_Detection": 2063.06,
    "EMA_Breached_At_Detection": true,
    "Below_EMA": true,
    "Surge_Gain_Pct": 21.39,
    "Surge_Candles": 13,
    "Surge_Allowed_Reds": 4,
    "Surge_Start": "2026-03-30",
    "Surge_End": "2026-04-24",
    "Days_Since_Surge_End": 40,
    "Prev_Pullup_High": 2274.78,
    "Lifetime_52W_High": 2326.32,
    "Suggested_Strike": 2200.0,
    "Expiry": "30-Jun-2026",
    "CE_LTP": 9.65,
    "CE_OI": 2011,
    "IV_Pct": 26.9,
    "CE_30d_High": 87.75,
    "CE_Above_30d_High": false,
    "Remark": "CE Below 30d High",
    "NSE_Hist_Calls": 1,
    "BCS_Hedge_Strike": 2300.0,
    "BCS_Hedge_CE_LTP": 4.0,
    "BCS_Hedge_CE_OI": 652,
    "BCS_Spread_Width": 100.0,
    "BCS_Net_Premium": 5.65,
    "BCS_Max_Profit": 5.65,
    "BCS_Max_Loss": 94.35,
    "BCS_Breakeven": 2205.65,
    "BCS_Risk_Reward": 16.7,
    "Status": "Momentum Lost",
    "Sell_Alert_Sent": false,
    "Breakdown_Date": "2026-06-01",
    "Sell_Zone_EMA_Confirmed": true,
    "Sell_Zone_EMA_Confirm_Date": "2026-05-26",
    "Scanned_At": "2026-06-03 12:55:10"
  },
  {
    "Ticker": "CAMS",
    "Today_Close": 752.3,
    "Surge_High": 778.05,
    "Yesterday_High": 792.5,
    "Yesterday_Close": 769.1,
    "Yesterday_Low": 765.35,
    "Drop_Pct": 1.06,
    "Breakdown_Volume": 1906544,
    "Avg_Volume_20d": 2131344,
    "Volume_Ratio": 0.89,
    "EMA_At_Detection": 776.24,
    "EMA_Breached_At_Detection": true,
    "Below_EMA": true,
    "Surge_Gain_Pct": 23.11,
    "Surge_Candles": 13,
    "Surge_Allowed_Reds": 3,
    "Surge_Start": "2026-03-30",
    "Surge_End": "2026-04-23",
    "Days_Since_Surge_End": 41,
    "Prev_Pullup_High": 844.9,
    "Lifetime_52W_High": 844.9,
    "Suggested_Strike": 800.0,
    "Expiry": "30-Jun-2026",
    "CE_LTP": 10.9,
    "CE_OI": 571,
    "IV_Pct": 32.7,
    "CE_30d_High": 59.95,
    "CE_Above_30d_High": false,
    "Remark": "CE Below 30d High",
    "NSE_Hist_Calls": 1,
    "BCS_Hedge_Strike": 850.0,
    "BCS_Hedge_CE_LTP": 3.3,
    "BCS_Hedge_CE_OI": 130,
    "BCS_Spread_Width": 50.0,
    "BCS_Net_Premium": 7.6,
    "BCS_Max_Profit": 7.6,
    "BCS_Max_Loss": 42.4,
    "BCS_Breakeven": 807.6,
    "BCS_Risk_Reward": 5.58,
    "Status": "Momentum Lost",
    "Sell_Alert_Sent": false,
    "Breakdown_Date": "2026-05-22",
    "Sell_Zone_EMA_Confirmed": true,
    "Sell_Zone_EMA_Confirm_Date": "2026-05-22",
    "Scanned_At": "2026-06-03 12:55:24"
  },
  {
    "Ticker": "CONCOR",
    "Today_Close": 448.1,
    "Surge_High": 537.0,
    "Yesterday_High": 464.15,
    "Yesterday_Close": 459.45,
    "Yesterday_Low": 455.5,
    "Drop_Pct": 1.62,
    "Breakdown_Volume": 1038902,
    "Avg_Volume_20d": 1804000,
    "Volume_Ratio": 0.58,
    "EMA_At_Detection": 471.67,
    "EMA_Breached_At_Detection": true,
    "Below_EMA": true,
    "Surge_Gain_Pct": 25.73,
    "Surge_Candles": 17,
    "Surge_Allowed_Reds": 10,
    "Surge_Start": "2026-03-30",
    "Surge_End": "2026-05-08",
    "Days_Since_Surge_End": 26,
    "Prev_Pullup_High": 537.0,
    "Lifetime_52W_High": 563.15,
    "Suggested_Strike": 550.0,
    "Expiry": "30-Jun-2026",
    "CE_LTP": 0.55,
    "CE_OI": 438,
    "IV_Pct": 38.4,
    "CE_30d_High": 18.0,
    "CE_Above_30d_High": false,
    "Remark": "CE Below 30d High",
    "NSE_Hist_Calls": 1,
    "BCS_Hedge_Strike": 600.0,
    "BCS_Hedge_CE_LTP": 0.25,
    "BCS_Hedge_CE_OI": 101,
    "BCS_Spread_Width": 50.0,
    "BCS_Net_Premium": 0.3,
    "BCS_Max_Profit": 0.3,
    "BCS_Max_Loss": 49.7,
    "BCS_Breakeven": 550.3,
    "BCS_Risk_Reward": 165.67,
    "Status": "Momentum Lost",
    "Sell_Alert_Sent": false,
    "Breakdown_Date": "2026-06-03",
    "Sell_Zone_EMA_Confirmed": true,
    "Sell_Zone_EMA_Confirm_Date": "2026-05-26",
    "Scanned_At": "2026-06-03 12:55:37"
  },
  {
    "Ticker": "DLF",
    "Today_Close": 577.1,
    "Surge_High": 614.8,
    "Yesterday_High": 607.9,
    "Yesterday_Close": 590.6,
    "Yesterday_Low": 586.55,
    "Drop_Pct": 1.11,
    "Breakdown_Volume": 2942650,
    "Avg_Volume_20d": 3746458,
    "Volume_Ratio": 0.79,
    "EMA_At_Detection": 587.46,
    "EMA_Breached_At_Detection": true,
    "Below_EMA": true,
    "Surge_Gain_Pct": 21.14,
    "Surge_Candles": 9,
    "Surge_Allowed_Reds": 6,
    "Surge_Start": "2026-03-30",
    "Surge_End": "2026-04-22",
    "Days_Since_Surge_End": 42,
    "Prev_Pullup_High": 676.6,
    "Lifetime_52W_High": 794.8,
    "Suggested_Strike": 615.0,
    "Expiry": "30-Jun-2026",
    "CE_LTP": 8.5,
    "CE_OI": 87,
    "IV_Pct": 33.5,
    "CE_30d_High": 27.95,
    "CE_Above_30d_High": false,
    "Remark": "CE Below 30d High",
    "NSE_Hist_Calls": 1,
    "BCS_Hedge_Strike": null,
    "BCS_Hedge_CE_LTP": null,
    "BCS_Hedge_CE_OI": null,
    "BCS_Spread_Width": null,
    "BCS_Net_Premium": null,
    "BCS_Max_Profit": null,
    "BCS_Max_Loss": null,
    "BCS_Breakeven": null,
    "BCS_Risk_Reward": null,
    "Status": "Momentum Lost",
    "Sell_Alert_Sent": false,
    "Breakdown_Date": "2026-06-01",
    "Sell_Zone_EMA_Confirmed": true,
    "Sell_Zone_EMA_Confirm_Date": "2026-05-12",
    "Scanned_At": "2026-06-03 12:55:54"
  },
  {
    "Ticker": "EXIDEIND",
    "Today_Close": 366.25,
    "Surge_High": 379.9,
    "Yesterday_High": 352.05,
    "Yesterday_Close": 349.05,
    "Yesterday_Low": 347.4,
    "Drop_Pct": 1.31,
    "Breakdown_Volume": 2692440,
    "Avg_Volume_20d": 4502731,
    "Volume_Ratio": 0.6,
    "EMA_At_Detection": 350.12,
    "EMA_Breached_At_Detection": true,
    "Below_EMA": true,
    "Surge_Gain_Pct": 23.15,
    "Surge_Candles": 7,
    "Surge_Allowed_Reds": 8,
    "Surge_Start": "2026-03-30",
    "Surge_End": "2026-04-22",
    "Days_Since_Surge_End": 34,
    "Prev_Pullup_High": 379.9,
    "Lifetime_52W_High": 431.0,
    "Suggested_Strike": 380,
    "Expiry": "30-Jun-2026",
    "CE_LTP": 17.75,
    "CE_OI": 21,
    "IV_Pct": 32.4,
    "CE_30d_High": "N/A",
    "CE_Above_30d_High": "Unverified",
    "Remark": "Unverified 30d High",
    "NSE_Hist_Calls": 1,
    "BCS_Hedge_Strike": 402.5,
    "BCS_Hedge_CE_LTP": 1.65,
    "BCS_Hedge_CE_OI": 31,
    "BCS_Spread_Width": 40.0,
    "BCS_Net_Premium": 16.1,
    "BCS_Max_Profit": 16.1,
    "BCS_Max_Loss": 23.9,
    "BCS_Breakeven": 378.6,
    "BCS_Risk_Reward": 1.48,
    "Status": "Momentum Lost",
    "Sell_Alert_Sent": false,
    "Breakdown_Date": "2026-05-18",
    "Sell_Zone_EMA_Confirmed": true,
    "Sell_Zone_EMA_Confirm_Date": "2026-05-18",
    "Scanned_At": "2026-05-26 16:47:37"
  },
  {
    "Ticker": "GAIL",
    "Today_Close": 163.44,
    "Surge_High": 166.8,
    "Yesterday_High": 169.0,
    "Yesterday_Close": 169.0,
    "Yesterday_Low": 169.0,
    "Drop_Pct": 2.66,
    "Breakdown_Volume": 26119462,
    "Avg_Volume_20d": 10234482,
    "Volume_Ratio": 2.55,
    "EMA_At_Detection": 164.85,
    "EMA_Breached_At_Detection": true,
    "Below_EMA": true,
    "Surge_Gain_Pct": 21.09,
    "Surge_Candles": 10,
    "Surge_Allowed_Reds": 6,
    "Surge_Start": "2026-03-27",
    "Surge_End": "2026-04-22",
    "Days_Since_Surge_End": 42,
    "Prev_Pullup_High": 171.46,
    "Lifetime_52W_High": 181.22,
    "Suggested_Strike": 167.0,
    "Expiry": "30-Jun-2026",
    "CE_LTP": 3.27,
    "CE_OI": 170,
    "IV_Pct": 25.3,
    "CE_30d_High": 9.82,
    "CE_Above_30d_High": false,
    "Remark": "CE Below 30d High",
    "NSE_Hist_Calls": 1,
    "BCS_Hedge_Strike": 177.0,
    "BCS_Hedge_CE_LTP": 1.08,
    "BCS_Hedge_CE_OI": 68,
    "BCS_Spread_Width": 10.0,
    "BCS_Net_Premium": 2.19,
    "BCS_Max_Profit": 2.19,
    "BCS_Max_Loss": 7.81,
    "BCS_Breakeven": 169.19,
    "BCS_Risk_Reward": 3.57,
    "Status": "Momentum Lost",
    "Sell_Alert_Sent": false,
    "Breakdown_Date": "2026-05-29",
    "Sell_Zone_EMA_Confirmed": true,
    "Sell_Zone_EMA_Confirm_Date": "2026-05-19",
    "Scanned_At": "2026-06-03 12:56:18"
  },
  {
    "Ticker": "GODREJPROP",
    "Today_Close": 1690.9,
    "Surge_High": 1849.0,
    "Yesterday_High": 1834.8,
    "Yesterday_Close": 1762.7,
    "Yesterday_Low": 1750.0,
    "Drop_Pct": 2.05,
    "Breakdown_Volume": 539239,
    "Avg_Volume_20d": 903619,
    "Volume_Ratio": 0.6,
    "EMA_At_Detection": 1748.45,
    "EMA_Breached_At_Detection": true,
    "Below_EMA": true,
    "Surge_Gain_Pct": 24.53,
    "Surge_Candles": 9,
    "Surge_Allowed_Reds": 6,
    "Surge_Start": "2026-03-30",
    "Surge_End": "2026-04-22",
    "Days_Since_Surge_End": 42,
    "Prev_Pullup_High": 1951.9,
    "Lifetime_52W_High": 2352.0,
    "Suggested_Strike": 1900.0,
    "Expiry": "30-Jun-2026",
    "CE_LTP": 10.35,
    "CE_OI": 2049,
    "IV_Pct": 35.3,
    "CE_30d_High": 113.8,
    "CE_Above_30d_High": false,
    "Remark": "CE Below 30d High",
    "NSE_Hist_Calls": 1,
    "BCS_Hedge_Strike": 2000.0,
    "BCS_Hedge_CE_LTP": 3.75,
    "BCS_Hedge_CE_OI": 546,
    "BCS_Spread_Width": 100.0,
    "BCS_Net_Premium": 6.6,
    "BCS_Max_Profit": 6.6,
    "BCS_Max_Loss": 93.4,
    "BCS_Breakeven": 1906.6,
    "BCS_Risk_Reward": 14.15,
    "Status": "Momentum Lost",
    "Sell_Alert_Sent": false,
    "Breakdown_Date": "2026-06-01",
    "Sell_Zone_EMA_Confirmed": true,
    "Sell_Zone_EMA_Confirm_Date": "2026-05-18",
    "Scanned_At": "2026-06-03 12:56:39"
  },
  {
    "Ticker": "HDFCAMC",
    "Today_Close": 2478.9,
    "Surge_High": 2816.8,
    "Yesterday_High": 2594.7,
    "Yesterday_Close": 2583.5,
    "Yesterday_Low": 2540.0,
    "Drop_Pct": 2.41,
    "Breakdown_Volume": 566514,
    "Avg_Volume_20d": 851727,
    "Volume_Ratio": 0.67,
    "EMA_At_Detection": 2630.24,
    "EMA_Breached_At_Detection": true,
    "Below_EMA": true,
    "Surge_Gain_Pct": 26.06,
    "Surge_Candles": 8,
    "Surge_Allowed_Reds": 6,
    "Surge_Start": "2026-03-30",
    "Surge_End": "2026-04-21",
    "Days_Since_Surge_End": 43,
    "Prev_Pullup_High": 2901.5,
    "Lifetime_52W_High": 2967.25,
    "Suggested_Strike": 2820.0,
    "Expiry": "30-Jun-2026",
    "CE_LTP": 8.85,
    "CE_OI": 50,
    "IV_Pct": 32.9,
    "CE_30d_High": 163.75,
    "CE_Above_30d_High": false,
    "Remark": "CE Below 30d High",
    "NSE_Hist_Calls": 1,
    "BCS_Hedge_Strike": null,
    "BCS_Hedge_CE_LTP": null,
    "BCS_Hedge_CE_OI": null,
    "BCS_Spread_Width": null,
    "BCS_Net_Premium": null,
    "BCS_Max_Profit": null,
    "BCS_Max_Loss": null,
    "BCS_Breakeven": null,
    "BCS_Risk_Reward": null,
    "Status": "Momentum Lost",
    "Sell_Alert_Sent": false,
    "Breakdown_Date": "2026-06-03",
    "Sell_Zone_EMA_Confirmed": true,
    "Sell_Zone_EMA_Confirm_Date": "2026-05-27",
    "Scanned_At": "2026-06-03 12:56:57"
  },
  {
    "Ticker": "HAL",
    "Today_Close": 4232.0,
    "Surge_High": 4399.4,
    "Yesterday_High": 4413.0,
    "Yesterday_Close": 4413.0,
    "Yesterday_Low": 4413.0,
    "Drop_Pct": 2.47,
    "Breakdown_Volume": 4597399,
    "Avg_Volume_20d": 1362386,
    "Volume_Ratio": 3.37,
    "EMA_At_Detection": 4395.99,
    "EMA_Breached_At_Detection": true,
    "Below_EMA": true,
    "Surge_Gain_Pct": 25.83,
    "Surge_Candles": 11,
    "Surge_Allowed_Reds": 1,
    "Surge_Start": "2026-03-30",
    "Surge_End": "2026-04-17",
    "Days_Since_Surge_End": 47,
    "Prev_Pullup_High": 4836.3,
    "Lifetime_52W_High": 4936.98,
    "Suggested_Strike": 4400.0,
    "Expiry": "30-Jun-2026",
    "CE_LTP": 71.85,
    "CE_OI": 1841,
    "IV_Pct": 28.4,
    "CE_30d_High": 485.0,
    "CE_Above_30d_High": false,
    "Remark": "CE Below 30d High",
    "NSE_Hist_Calls": 1,
    "BCS_Hedge_Strike": 4600.0,
    "BCS_Hedge_CE_LTP": 28.85,
    "BCS_Hedge_CE_OI": 1372,
    "BCS_Spread_Width": 200.0,
    "BCS_Net_Premium": 43.0,
    "BCS_Max_Profit": 43.0,
    "BCS_Max_Loss": 157.0,
    "BCS_Breakeven": 4443.0,
    "BCS_Risk_Reward": 3.65,
    "Status": "Momentum Lost",
    "Sell_Alert_Sent": false,
    "Breakdown_Date": "2026-05-29",
    "Sell_Zone_EMA_Confirmed": true,
    "Sell_Zone_EMA_Confirm_Date": "2026-05-18",
    "Scanned_At": "2026-06-03 12:57:17"
  },
  {
    "Ticker": "IEX",
    "Today_Close": 123.08,
    "Surge_High": 134.67,
    "Yesterday_High": 129.8,
    "Yesterday_Close": 128.31,
    "Yesterday_Low": 126.43,
    "Drop_Pct": 0.82,
    "Breakdown_Volume": 4525379,
    "Avg_Volume_20d": 4904783,
    "Volume_Ratio": 0.92,
    "EMA_At_Detection": 126.67,
    "EMA_Breached_At_Detection": true,
    "Below_EMA": true,
    "Surge_Gain_Pct": 18.35,
    "Surge_Candles": 10,
    "Surge_Allowed_Reds": 2,
    "Surge_Start": "2026-03-30",
    "Surge_End": "2026-04-17",
    "Days_Since_Surge_End": 47,
    "Prev_Pullup_High": 135.2,
    "Lifetime_52W_High": 155.9,
    "Suggested_Strike": 135.0,
    "Expiry": "30-Jun-2026",
    "CE_LTP": 1.13,
    "CE_OI": 805,
    "IV_Pct": 34.4,
    "CE_30d_High": 7.74,
    "CE_Above_30d_High": false,
    "Remark": "CE Below 30d High",
    "NSE_Hist_Calls": 1,
    "BCS_Hedge_Strike": 145.0,
    "BCS_Hedge_CE_LTP": 0.42,
    "BCS_Hedge_CE_OI": 123,
    "BCS_Spread_Width": 10.0,
    "BCS_Net_Premium": 0.71,
    "BCS_Max_Profit": 0.71,
    "BCS_Max_Loss": 9.29,
    "BCS_Breakeven": 135.71,
    "BCS_Risk_Reward": 13.08,
    "Status": "Momentum Lost",
    "Sell_Alert_Sent": false,
    "Breakdown_Date": "2026-06-01",
    "Sell_Zone_EMA_Confirmed": true,
    "Sell_Zone_EMA_Confirm_Date": "2026-05-12",
    "Scanned_At": "2026-06-03 12:57:54"
  },
  {
    "Ticker": "IRFC",
    "Today_Close": 95.2,
    "Surge_High": 106.78,
    "Yesterday_High": 100.14,
    "Yesterday_Close": 97.51,
    "Yesterday_Low": 97.02,
    "Drop_Pct": 0.77,
    "Breakdown_Volume": 7942957,
    "Avg_Volume_20d": 10212741,
    "Volume_Ratio": 0.78,
    "EMA_At_Detection": 98.42,
    "EMA_Breached_At_Detection": true,
    "Below_EMA": true,
    "Surge_Gain_Pct": 20.19,
    "Surge_Candles": 10,
    "Surge_Allowed_Reds": 2,
    "Surge_Start": "2026-03-30",
    "Surge_End": "2026-04-17",
    "Days_Since_Surge_End": 47,
    "Prev_Pullup_High": 118.53,
    "Lifetime_52W_High": 135.73,
    "Suggested_Strike": 107.0,
    "Expiry": "30-Jun-2026",
    "CE_LTP": 0.54,
    "CE_OI": 212,
    "IV_Pct": 34.6,
    "CE_30d_High": 7.3,
    "CE_Above_30d_High": false,
    "Remark": "CE Below 30d High",
    "NSE_Hist_Calls": 1,
    "BCS_Hedge_Strike": null,
    "BCS_Hedge_CE_LTP": null,
    "BCS_Hedge_CE_OI": null,
    "BCS_Spread_Width": null,
    "BCS_Net_Premium": null,
    "BCS_Max_Profit": null,
    "BCS_Max_Loss": null,
    "BCS_Breakeven": null,
    "BCS_Risk_Reward": null,
    "Status": "Momentum Lost",
    "Sell_Alert_Sent": false,
    "Breakdown_Date": "2026-06-01",
    "Sell_Zone_EMA_Confirmed": true,
    "Sell_Zone_EMA_Confirm_Date": "2026-05-18",
    "Scanned_At": "2026-06-03 12:58:10"
  },
  {
    "Ticker": "IREDA",
    "Today_Close": 121.97,
    "Surge_High": 134.2,
    "Yesterday_High": 125.3,
    "Yesterday_Close": 124.93,
    "Yesterday_Low": 122.8,
    "Drop_Pct": 0.68,
    "Breakdown_Volume": 5150969,
    "Avg_Volume_20d": 8268712,
    "Volume_Ratio": 0.62,
    "EMA_At_Detection": 127.2,
    "EMA_Breached_At_Detection": true,
    "Below_EMA": true,
    "Surge_Gain_Pct": 22.7,
    "Surge_Candles": 9,
    "Surge_Allowed_Reds": 3,
    "Surge_Start": "2026-03-30",
    "Surge_End": "2026-04-17",
    "Days_Since_Surge_End": 47,
    "Prev_Pullup_High": 142.85,
    "Lifetime_52W_High": 162.49,
    "Suggested_Strike": 135.0,
    "Expiry": "30-Jun-2026",
    "CE_LTP": 0.85,
    "CE_OI": 1247,
    "IV_Pct": 33.3,
    "CE_30d_High": 12.91,
    "CE_Above_30d_High": false,
    "Remark": "CE Below 30d High",
    "NSE_Hist_Calls": 1,
    "BCS_Hedge_Strike": 145.0,
    "BCS_Hedge_CE_LTP": 0.35,
    "BCS_Hedge_CE_OI": 243,
    "BCS_Spread_Width": 10.0,
    "BCS_Net_Premium": 0.5,
    "BCS_Max_Profit": 0.5,
    "BCS_Max_Loss": 9.5,
    "BCS_Breakeven": 135.5,
    "BCS_Risk_Reward": 19.0,
    "Status": "Momentum Lost",
    "Sell_Alert_Sent": false,
    "Breakdown_Date": "2026-06-03",
    "Sell_Zone_EMA_Confirmed": true,
    "Sell_Zone_EMA_Confirm_Date": "2026-05-12",
    "Scanned_At": "2026-06-03 12:58:25"
  },
  {
    "Ticker": "JUBLFOOD",
    "Today_Close": 429.35,
    "Surge_High": 494.65,
    "Yesterday_High": 446.25,
    "Yesterday_Close": 438.75,
    "Yesterday_Low": 436.1,
    "Drop_Pct": 1.39,
    "Breakdown_Volume": 4452681,
    "Avg_Volume_20d": 2718809,
    "Volume_Ratio": 1.64,
    "EMA_At_Detection": 447.27,
    "EMA_Breached_At_Detection": true,
    "Below_EMA": true,
    "Surge_Gain_Pct": 19.35,
    "Surge_Candles": 8,
    "Surge_Allowed_Reds": 3,
    "Surge_Start": "2026-04-07",
    "Surge_End": "2026-04-22",
    "Days_Since_Surge_End": 42,
    "Prev_Pullup_High": 575.0,
    "Lifetime_52W_High": 637.3,
    "Suggested_Strike": 500.0,
    "Expiry": "30-Jun-2026",
    "CE_LTP": 1.35,
    "CE_OI": 999,
    "IV_Pct": 36.3,
    "CE_30d_High": 18.0,
    "CE_Above_30d_High": false,
    "Remark": "CE Below 30d High",
    "NSE_Hist_Calls": 1,
    "BCS_Hedge_Strike": 550.0,
    "BCS_Hedge_CE_LTP": 0.3,
    "BCS_Hedge_CE_OI": 27,
    "BCS_Spread_Width": 50.0,
    "BCS_Net_Premium": 1.05,
    "BCS_Max_Profit": 1.05,
    "BCS_Max_Loss": 48.95,
    "BCS_Breakeven": 501.05,
    "BCS_Risk_Reward": 46.62,
    "Status": "Momentum Lost",
    "Sell_Alert_Sent": false,
    "Breakdown_Date": "2026-05-26",
    "Sell_Zone_EMA_Confirmed": true,
    "Sell_Zone_EMA_Confirm_Date": "2026-05-26",
    "Scanned_At": "2026-06-03 12:59:07"
  },
  {
    "Ticker": "KALYANKJIL",
    "Today_Close": 344.95,
    "Surge_High": 451.55,
    "Yesterday_High": 361.75,
    "Yesterday_Close": 353.05,
    "Yesterday_Low": 352.0,
    "Drop_Pct": 1.68,
    "Breakdown_Volume": 7652972,
    "Avg_Volume_20d": 8572548,
    "Volume_Ratio": 0.89,
    "EMA_At_Detection": 372.03,
    "EMA_Breached_At_Detection": true,
    "Below_EMA": true,
    "Surge_Gain_Pct": 19.49,
    "Surge_Candles": 6,
    "Surge_Allowed_Reds": 2,
    "Surge_Start": "2026-03-30",
    "Surge_End": "2026-04-10",
    "Days_Since_Surge_End": 54,
    "Prev_Pullup_High": 452.6,
    "Lifetime_52W_High": 535.0,
    "Suggested_Strike": 480.0,
    "Expiry": "30-Jun-2026",
    "CE_LTP": 0.35,
    "CE_OI": 105,
    "IV_Pct": 55.8,
    "CE_30d_High": 12.8,
    "CE_Above_30d_High": false,
    "Remark": "CE Below 30d High",
    "NSE_Hist_Calls": 1,
    "BCS_Hedge_Strike": null,
    "BCS_Hedge_CE_LTP": null,
    "BCS_Hedge_CE_OI": null,
    "BCS_Spread_Width": null,
    "BCS_Net_Premium": null,
    "BCS_Max_Profit": null,
    "BCS_Max_Loss": null,
    "BCS_Breakeven": null,
    "BCS_Risk_Reward": null,
    "Status": "Momentum Lost",
    "Sell_Alert_Sent": false,
    "Breakdown_Date": "2026-05-18",
    "Sell_Zone_EMA_Confirmed": true,
    "Sell_Zone_EMA_Confirm_Date": "2026-05-18",
    "Scanned_At": "2026-06-03 12:59:24"
  },
  {
    "Ticker": "LTF",
    "Today_Close": 264.9,
    "Surge_High": 292.28,
    "Yesterday_High": 289.4,
    "Yesterday_Close": 286.6,
    "Yesterday_Low": 281.1,
    "Drop_Pct": 3.5,
    "Breakdown_Volume": 6477563,
    "Avg_Volume_20d": 4878490,
    "Volume_Ratio": 1.33,
    "EMA_At_Detection": 278.66,
    "EMA_Breached_At_Detection": true,
    "Below_EMA": true,
    "Surge_Gain_Pct": 22.41,
    "Surge_Candles": 10,
    "Surge_Allowed_Reds": 5,
    "Surge_Start": "2026-03-30",
    "Surge_End": "2026-04-22",
    "Days_Since_Surge_End": 42,
    "Prev_Pullup_High": 307.34,
    "Lifetime_52W_High": 326.09,
    "Suggested_Strike": 300.0,
    "Expiry": "30-Jun-2026",
    "CE_LTP": 1.4,
    "CE_OI": 919,
    "IV_Pct": 35.5,
    "CE_30d_High": 15.0,
    "CE_Above_30d_High": false,
    "Remark": "CE Below 30d High",
    "NSE_Hist_Calls": 1,
    "BCS_Hedge_Strike": 320.0,
    "BCS_Hedge_CE_LTP": 0.55,
    "BCS_Hedge_CE_OI": 337,
    "BCS_Spread_Width": 20.0,
    "BCS_Net_Premium": 0.85,
    "BCS_Max_Profit": 0.85,
    "BCS_Max_Loss": 19.15,
    "BCS_Breakeven": 300.85,
    "BCS_Risk_Reward": 22.53,
    "Status": "Momentum Lost",
    "Sell_Alert_Sent": false,
    "Breakdown_Date": "2026-06-01",
    "Sell_Zone_EMA_Confirmed": true,
    "Sell_Zone_EMA_Confirm_Date": "2026-05-21",
    "Scanned_At": "2026-06-03 12:59:40"
  },
  {
    "Ticker": "LT",
    "Today_Close": 3939.4,
    "Surge_High": 3993.0,
    "Yesterday_High": 4128.0,
    "Yesterday_Close": 4076.5,
    "Yesterday_Low": 4045.0,
    "Drop_Pct": 0.85,
    "Breakdown_Volume": 1409388,
    "Avg_Volume_20d": 2545538,
    "Volume_Ratio": 0.55,
    "EMA_At_Detection": 4004.58,
    "EMA_Breached_At_Detection": true,
    "Below_EMA": false,
    "Surge_Gain_Pct": 19.85,
    "Surge_Candles": 7,
    "Surge_Allowed_Reds": 3,
    "Surge_Start": "2026-03-23",
    "Surge_End": "2026-04-08",
    "Days_Since_Surge_End": 56,
    "Prev_Pullup_High": 4397.05,
    "Lifetime_52W_High": 4397.05,
    "Suggested_Strike": 4000.0,
    "Expiry": "30-Jun-2026",
    "CE_LTP": 80.0,
    "CE_OI": 3734,
    "IV_Pct": 23.1,
    "CE_30d_High": 253.0,
    "CE_Above_30d_High": false,
    "Remark": "CE Below 30d High",
    "NSE_Hist_Calls": 1,
    "BCS_Hedge_Strike": 4200.0,
    "BCS_Hedge_CE_LTP": 23.5,
    "BCS_Hedge_CE_OI": 3103,
    "BCS_Spread_Width": 200.0,
    "BCS_Net_Premium": 56.5,
    "BCS_Max_Profit": 56.5,
    "BCS_Max_Loss": 143.5,
    "BCS_Breakeven": 4056.5,
    "BCS_Risk_Reward": 2.54,
    "Status": "Momentum Lost",
    "Sell_Alert_Sent": false,
    "Breakdown_Date": "2026-06-01",
    "Sell_Zone_EMA_Confirmed": true,
    "Sell_Zone_EMA_Confirm_Date": "2026-05-12",
    "Scanned_At": "2026-06-03 12:59:56"
  },
  {
    "Ticker": "LODHA",
    "Today_Close": 877.05,
    "Surge_High": 878.45,
    "Yesterday_High": 969.0,
    "Yesterday_Close": 938.1,
    "Yesterday_Low": 923.6,
    "Drop_Pct": 3.31,
    "Breakdown_Volume": 2050481,
    "Avg_Volume_20d": 2325349,
    "Volume_Ratio": 0.88,
    "EMA_At_Detection": 906.98,
    "EMA_Breached_At_Detection": true,
    "Below_EMA": true,
    "Surge_Gain_Pct": 29.03,
    "Surge_Candles": 9,
    "Surge_Allowed_Reds": 2,
    "Surge_Start": "2026-03-30",
    "Surge_End": "2026-04-16",
    "Days_Since_Surge_End": 48,
    "Prev_Pullup_High": 1113.2,
    "Lifetime_52W_High": 1244.0,
    "Suggested_Strike": 900.0,
    "Expiry": "30-Jun-2026",
    "CE_LTP": 30.65,
    "CE_OI": 610,
    "IV_Pct": 40.8,
    "CE_30d_High": 75.0,
    "CE_Above_30d_High": false,
    "Remark": "CE Below 30d High",
    "NSE_Hist_Calls": 1,
    "BCS_Hedge_Strike": 950.0,
    "BCS_Hedge_CE_LTP": 15.4,
    "BCS_Hedge_CE_OI": 916,
    "BCS_Spread_Width": 50.0,
    "BCS_Net_Premium": 15.25,
    "BCS_Max_Profit": 15.25,
    "BCS_Max_Loss": 34.75,
    "BCS_Breakeven": 915.25,
    "BCS_Risk_Reward": 2.28,
    "Status": "Momentum Lost",
    "Sell_Alert_Sent": false,
    "Breakdown_Date": "2026-06-01",
    "Sell_Zone_EMA_Confirmed": true,
    "Sell_Zone_EMA_Confirm_Date": "2026-05-13",
    "Scanned_At": "2026-06-03 13:00:10"
  },
  {
    "Ticker": "MPHASIS",
    "Today_Close": 2295.3,
    "Surge_High": 2479.0,
    "Yesterday_High": 2430.5,
    "Yesterday_Close": 2387.7,
    "Yesterday_Low": 2323.0,
    "Drop_Pct": 1.19,
    "Breakdown_Volume": 436202,
    "Avg_Volume_20d": 535183,
    "Volume_Ratio": 0.82,
    "EMA_At_Detection": 2280.4,
    "EMA_Breached_At_Detection": true,
    "Below_EMA": false,
    "Surge_Gain_Pct": 19.93,
    "Surge_Candles": 9,
    "Surge_Allowed_Reds": 3,
    "Surge_Start": "2026-03-30",
    "Surge_End": "2026-04-17",
    "Days_Since_Surge_End": 47,
    "Prev_Pullup_High": 2975.0,
    "Lifetime_52W_High": 3037.2,
    "Suggested_Strike": 2500.0,
    "Expiry": "30-Jun-2026",
    "CE_LTP": 20.75,
    "CE_OI": 321,
    "IV_Pct": 32.5,
    "CE_30d_High": 66.3,
    "CE_Above_30d_High": false,
    "Remark": "CE Below 30d High",
    "NSE_Hist_Calls": 1,
    "BCS_Hedge_Strike": null,
    "BCS_Hedge_CE_LTP": null,
    "BCS_Hedge_CE_OI": null,
    "BCS_Spread_Width": null,
    "BCS_Net_Premium": null,
    "BCS_Max_Profit": null,
    "BCS_Max_Loss": null,
    "BCS_Breakeven": null,
    "BCS_Risk_Reward": null,
    "Status": "Momentum Lost",
    "Sell_Alert_Sent": false,
    "Breakdown_Date": "2026-06-03",
    "Sell_Zone_EMA_Confirmed": true,
    "Sell_Zone_EMA_Confirm_Date": "2026-05-14",
    "Scanned_At": "2026-06-03 13:00:34"
  },
  {
    "Ticker": "NBCC",
    "Today_Close": 101.01,
    "Surge_High": 96.5,
    "Yesterday_High": 106.86,
    "Yesterday_Close": 104.11,
    "Yesterday_Low": 102.03,
    "Drop_Pct": 1.0,
    "Breakdown_Volume": 11585997,
    "Avg_Volume_20d": 19758730,
    "Volume_Ratio": 0.59,
    "EMA_At_Detection": 99.91,
    "EMA_Breached_At_Detection": true,
    "Below_EMA": false,
    "Surge_Gain_Pct": 23.08,
    "Surge_Candles": 12,
    "Surge_Allowed_Reds": 6,
    "Surge_Start": "2026-03-30",
    "Surge_End": "2026-04-27",
    "Days_Since_Surge_End": 37,
    "Prev_Pullup_High": 104.66,
    "Lifetime_52W_High": 125.69,
    "Suggested_Strike": 100.0,
    "Expiry": "30-Jun-2026",
    "CE_LTP": 5.19,
    "CE_OI": 626,
    "IV_Pct": 40.5,
    "CE_30d_High": 7.52,
    "CE_Above_30d_High": false,
    "Remark": "CE Below 30d High",
    "NSE_Hist_Calls": 1,
    "BCS_Hedge_Strike": 110.0,
    "BCS_Hedge_CE_LTP": 1.8,
    "BCS_Hedge_CE_OI": 1403,
    "BCS_Spread_Width": 10.0,
    "BCS_Net_Premium": 3.39,
    "BCS_Max_Profit": 3.39,
    "BCS_Max_Loss": 6.61,
    "BCS_Breakeven": 103.39,
    "BCS_Risk_Reward": 1.95,
    "Status": "Momentum Lost",
    "Sell_Alert_Sent": false,
    "Breakdown_Date": "2026-06-03",
    "Sell_Zone_EMA_Confirmed": true,
    "Sell_Zone_EMA_Confirm_Date": "2026-05-18",
    "Scanned_At": "2026-06-03 13:01:05"
  },
  {
    "Ticker": "NESTLEIND",
    "Today_Close": 1387.4,
    "Surge_High": 1470.0,
    "Yesterday_High": 1427.5,
    "Yesterday_Close": 1427.5,
    "Yesterday_Low": 1427.5,
    "Drop_Pct": 0.42,
    "Breakdown_Volume": 13063475,
    "Avg_Volume_20d": 1561355,
    "Volume_Ratio": 8.37,
    "EMA_At_Detection": 1426.99,
    "EMA_Breached_At_Detection": true,
    "Below_EMA": true,
    "Surge_Gain_Pct": 19.53,
    "Surge_Candles": 9,
    "Surge_Allowed_Reds": 3,
    "Surge_Start": "2026-04-13",
    "Surge_End": "2026-04-29",
    "Days_Since_Surge_End": 35,
    "Prev_Pullup_High": 1498.1,
    "Lifetime_52W_High": 1498.1,
    "Suggested_Strike": 1500.0,
    "Expiry": "30-Jun-2026",
    "CE_LTP": 4.5,
    "CE_OI": 419,
    "IV_Pct": 21.9,
    "CE_30d_High": 49.0,
    "CE_Above_30d_High": false,
    "Remark": "CE Below 30d High",
    "NSE_Hist_Calls": 1,
    "BCS_Hedge_Strike": 1600.0,
    "BCS_Hedge_CE_LTP": 0.85,
    "BCS_Hedge_CE_OI": 194,
    "BCS_Spread_Width": 100.0,
    "BCS_Net_Premium": 3.65,
    "BCS_Max_Profit": 3.65,
    "BCS_Max_Loss": 96.35,
    "BCS_Breakeven": 1503.65,
    "BCS_Risk_Reward": 26.4,
    "Status": "Momentum Lost",
    "Sell_Alert_Sent": false,
    "Breakdown_Date": "2026-05-29",
    "Sell_Zone_EMA_Confirmed": true,
    "Sell_Zone_EMA_Confirm_Date": "2026-05-20",
    "Scanned_At": "2026-06-03 13:01:29"
  },
  {
    "Ticker": "OBEROIRLTY",
    "Today_Close": 1637.4,
    "Surge_High": 1737.95,
    "Yesterday_High": 1744.0,
    "Yesterday_Close": 1707.1,
    "Yesterday_Low": 1684.2,
    "Drop_Pct": 2.07,
    "Breakdown_Volume": 304709,
    "Avg_Volume_20d": 423161,
    "Volume_Ratio": 0.72,
    "EMA_At_Detection": 1671.1,
    "EMA_Breached_At_Detection": true,
    "Below_EMA": true,
    "Surge_Gain_Pct": 20.55,
    "Surge_Candles": 9,
    "Surge_Allowed_Reds": 3,
    "Surge_Start": "2026-03-30",
    "Surge_End": "2026-04-17",
    "Days_Since_Surge_End": 47,
    "Prev_Pullup_High": 1751.83,
    "Lifetime_52W_High": 1828.96,
    "Suggested_Strike": 1740.0,
    "Expiry": "30-Jun-2026",
    "CE_LTP": 18.3,
    "CE_OI": 111,
    "IV_Pct": 28.7,
    "CE_30d_High": 97.65,
    "CE_Above_30d_High": false,
    "Remark": "CE Below 30d High",
    "NSE_Hist_Calls": 1,
    "BCS_Hedge_Strike": 1840.0,
    "BCS_Hedge_CE_LTP": 4.8,
    "BCS_Hedge_CE_OI": 550,
    "BCS_Spread_Width": 100.0,
    "BCS_Net_Premium": 13.5,
    "BCS_Max_Profit": 13.5,
    "BCS_Max_Loss": 86.5,
    "BCS_Breakeven": 1753.5,
    "BCS_Risk_Reward": 6.41,
    "Status": "Momentum Lost",
    "Sell_Alert_Sent": false,
    "Breakdown_Date": "2026-06-01",
    "Sell_Zone_EMA_Confirmed": true,
    "Sell_Zone_EMA_Confirm_Date": "2026-05-18",
    "Scanned_At": "2026-06-03 13:01:44"
  },
  {
    "Ticker": "PFC",
    "Today_Close": 413.15,
    "Surge_High": 486.5,
    "Yesterday_High": 431.9,
    "Yesterday_Close": 421.1,
    "Yesterday_Low": 420.05,
    "Drop_Pct": 1.67,
    "Breakdown_Volume": 6066023,
    "Avg_Volume_20d": 5672161,
    "Volume_Ratio": 1.07,
    "EMA_At_Detection": 427.86,
    "EMA_Breached_At_Detection": true,
    "Below_EMA": true,
    "Surge_Gain_Pct": 26.85,
    "Surge_Candles": 15,
    "Surge_Allowed_Reds": 4,
    "Surge_Start": "2026-03-30",
    "Surge_End": "2026-04-28",
    "Days_Since_Surge_End": 36,
    "Prev_Pullup_High": 486.5,
    "Lifetime_52W_High": 486.5,
    "Suggested_Strike": 500.0,
    "Expiry": "30-Jun-2026",
    "CE_LTP": 0.45,
    "CE_OI": 1049,
    "IV_Pct": 35.5,
    "CE_30d_High": 18.65,
    "CE_Above_30d_High": false,
    "Remark": "CE Below 30d High",
    "NSE_Hist_Calls": 1,
    "BCS_Hedge_Strike": null,
    "BCS_Hedge_CE_LTP": null,
    "BCS_Hedge_CE_OI": null,
    "BCS_Spread_Width": null,
    "BCS_Net_Premium": null,
    "BCS_Max_Profit": null,
    "BCS_Max_Loss": null,
    "BCS_Breakeven": null,
    "BCS_Risk_Reward": null,
    "Status": "Momentum Lost",
    "Sell_Alert_Sent": false,
    "Breakdown_Date": "2026-06-02",
    "Sell_Zone_EMA_Confirmed": true,
    "Sell_Zone_EMA_Confirm_Date": "2026-05-26",
    "Scanned_At": "2026-06-03 13:02:12"
  },
  {
    "Ticker": "PRESTIGE",
    "Today_Close": 1344.0,
    "Surge_High": 1423.6,
    "Yesterday_High": 1399.8,
    "Yesterday_Close": 1399.8,
    "Yesterday_Low": 1399.8,
    "Drop_Pct": 2.19,
    "Breakdown_Volume": 1176813,
    "Avg_Volume_20d": 605168,
    "Volume_Ratio": 1.94,
    "EMA_At_Detection": 1389.51,
    "EMA_Breached_At_Detection": true,
    "Below_EMA": true,
    "Surge_Gain_Pct": 24.77,
    "Surge_Candles": 9,
    "Surge_Allowed_Reds": 6,
    "Surge_Start": "2026-03-30",
    "Surge_End": "2026-04-22",
    "Days_Since_Surge_End": 42,
    "Prev_Pullup_High": 1604.7,
    "Lifetime_52W_High": 1805.2,
    "Suggested_Strike": 1440.0,
    "Expiry": "30-Jun-2026",
    "CE_LTP": 20.1,
    "CE_OI": 106,
    "IV_Pct": 35.3,
    "CE_30d_High": 52.4,
    "CE_Above_30d_High": false,
    "Remark": "CE Below 30d High",
    "NSE_Hist_Calls": 1,
    "BCS_Hedge_Strike": null,
    "BCS_Hedge_CE_LTP": null,
    "BCS_Hedge_CE_OI": null,
    "BCS_Spread_Width": null,
    "BCS_Net_Premium": null,
    "BCS_Max_Profit": null,
    "BCS_Max_Loss": null,
    "BCS_Breakeven": null,
    "BCS_Risk_Reward": null,
    "Status": "Momentum Lost",
    "Sell_Alert_Sent": false,
    "Breakdown_Date": "2026-05-29",
    "Sell_Zone_EMA_Confirmed": true,
    "Sell_Zone_EMA_Confirm_Date": "2026-05-13",
    "Scanned_At": "2026-06-03 13:02:27"
  },
  {
    "Ticker": "RECLTD",
    "Today_Close": 324.9,
    "Surge_High": 387.45,
    "Yesterday_High": 339.85,
    "Yesterday_Close": 331.4,
    "Yesterday_Low": 331.0,
    "Drop_Pct": 1.8,
    "Breakdown_Volume": 6501043,
    "Avg_Volume_20d": 4972532,
    "Volume_Ratio": 1.31,
    "EMA_At_Detection": 335.26,
    "EMA_Breached_At_Detection": true,
    "Below_EMA": true,
    "Surge_Gain_Pct": 25.65,
    "Surge_Candles": 13,
    "Surge_Allowed_Reds": 2,
    "Surge_Start": "2026-03-30",
    "Surge_End": "2026-04-22",
    "Days_Since_Surge_End": 42,
    "Prev_Pullup_High": 387.45,
    "Lifetime_52W_High": 387.45,
    "Suggested_Strike": 400.0,
    "Expiry": "30-Jun-2026",
    "CE_LTP": 0.25,
    "CE_OI": 1411,
    "IV_Pct": 36.1,
    "CE_30d_High": 15.75,
    "CE_Above_30d_High": false,
    "Remark": "CE Below 30d High",
    "NSE_Hist_Calls": 1,
    "BCS_Hedge_Strike": 420.0,
    "BCS_Hedge_CE_LTP": 0.2,
    "BCS_Hedge_CE_OI": 628,
    "BCS_Spread_Width": 20.0,
    "BCS_Net_Premium": 0.05,
    "BCS_Max_Profit": 0.05,
    "BCS_Max_Loss": 19.95,
    "BCS_Breakeven": 400.05,
    "BCS_Risk_Reward": 399.0,
    "Status": "Momentum Lost",
    "Sell_Alert_Sent": false,
    "Breakdown_Date": "2026-06-02",
    "Sell_Zone_EMA_Confirmed": true,
    "Sell_Zone_EMA_Confirm_Date": "2026-05-26",
    "Scanned_At": "2026-06-03 13:02:44"
  },
  {
    "Ticker": "SHRIRAMFIN",
    "Today_Close": 897.95,
    "Surge_High": 1062.7,
    "Yesterday_High": 917.95,
    "Yesterday_Close": 911.7,
    "Yesterday_Low": 900.2,
    "Drop_Pct": 0.25,
    "Breakdown_Volume": 3587410,
    "Avg_Volume_20d": 6119277,
    "Volume_Ratio": 0.59,
    "EMA_At_Detection": 929.56,
    "EMA_Breached_At_Detection": true,
    "Below_EMA": true,
    "Surge_Gain_Pct": 19.86,
    "Surge_Candles": 8,
    "Surge_Allowed_Reds": 6,
    "Surge_Start": "2026-03-30",
    "Surge_End": "2026-04-21",
    "Days_Since_Surge_End": 43,
    "Prev_Pullup_High": 1108.0,
    "Lifetime_52W_High": 1108.0,
    "Suggested_Strike": 1070.0,
    "Expiry": "30-Jun-2026",
    "CE_LTP": 1.5,
    "CE_OI": 39,
    "IV_Pct": 35.6,
    "CE_30d_High": 33.55,
    "CE_Above_30d_High": false,
    "Remark": "CE Below 30d High",
    "NSE_Hist_Calls": 1,
    "BCS_Hedge_Strike": null,
    "BCS_Hedge_CE_LTP": null,
    "BCS_Hedge_CE_OI": null,
    "BCS_Spread_Width": null,
    "BCS_Net_Premium": null,
    "BCS_Max_Profit": null,
    "BCS_Max_Loss": null,
    "BCS_Breakeven": null,
    "BCS_Risk_Reward": null,
    "Status": "Momentum Lost",
    "Sell_Alert_Sent": false,
    "Breakdown_Date": "2026-06-03",
    "Sell_Zone_EMA_Confirmed": true,
    "Sell_Zone_EMA_Confirm_Date": "2026-05-29",
    "Scanned_At": "2026-06-03 13:03:11"
  },
  {
    "Ticker": "SIEMENS",
    "Today_Close": 3714.0,
    "Surge_High": 3901.0,
    "Yesterday_High": 3937.3,
    "Yesterday_Close": 3844.0,
    "Yesterday_Low": 3744.6,
    "Drop_Pct": 0.89,
    "Breakdown_Volume": 526590,
    "Avg_Volume_20d": 589293,
    "Volume_Ratio": 0.89,
    "EMA_At_Detection": 3759.22,
    "EMA_Breached_At_Detection": true,
    "Below_EMA": true,
    "Surge_Gain_Pct": 31.67,
    "Surge_Candles": 12,
    "Surge_Allowed_Reds": 4,
    "Surge_Start": "2026-03-30",
    "Surge_End": "2026-04-23",
    "Days_Since_Surge_End": 41,
    "Prev_Pullup_High": 3930.0,
    "Lifetime_52W_High": 3937.3,
    "Suggested_Strike": 3950.0,
    "Expiry": "30-Jun-2026",
    "CE_LTP": 60.15,
    "CE_OI": 280,
    "IV_Pct": 34.6,
    "CE_30d_High": 221.7,
    "CE_Above_30d_High": false,
    "Remark": "CE Below 30d High",
    "NSE_Hist_Calls": 1,
    "BCS_Hedge_Strike": 4150.0,
    "BCS_Hedge_CE_LTP": 26.4,
    "BCS_Hedge_CE_OI": 104,
    "BCS_Spread_Width": 200.0,
    "BCS_Net_Premium": 33.75,
    "BCS_Max_Profit": 33.75,
    "BCS_Max_Loss": 166.25,
    "BCS_Breakeven": 3983.75,
    "BCS_Risk_Reward": 4.93,
    "Status": "Momentum Lost",
    "Sell_Alert_Sent": false,
    "Breakdown_Date": "2026-06-01",
    "Sell_Zone_EMA_Confirmed": true,
    "Sell_Zone_EMA_Confirm_Date": "2026-05-25",
    "Scanned_At": "2026-06-03 13:03:26"
  },
  {
    "Ticker": "PHOENIXLTD",
    "Today_Close": 1709.3,
    "Surge_High": 1813.5,
    "Yesterday_High": 1779.8,
    "Yesterday_Close": 1747.8,
    "Yesterday_Low": 1736.5,
    "Drop_Pct": 1.71,
    "Breakdown_Volume": 716902,
    "Avg_Volume_20d": 423123,
    "Volume_Ratio": 1.69,
    "EMA_At_Detection": 1756.96,
    "EMA_Breached_At_Detection": true,
    "Below_EMA": true,
    "Surge_Gain_Pct": 19.37,
    "Surge_Candles": 10,
    "Surge_Allowed_Reds": 3,
    "Surge_Start": "2026-03-27",
    "Surge_End": "2026-04-17",
    "Days_Since_Surge_End": 47,
    "Prev_Pullup_High": 1855.9,
    "Lifetime_52W_High": 1993.0,
    "Suggested_Strike": 1820.0,
    "Expiry": "30-Jun-2026",
    "CE_LTP": 20.85,
    "CE_OI": 47,
    "IV_Pct": 30.5,
    "CE_30d_High": 98.05,
    "CE_Above_30d_High": false,
    "Remark": "CE Below 30d High",
    "NSE_Hist_Calls": 1,
    "BCS_Hedge_Strike": null,
    "BCS_Hedge_CE_LTP": null,
    "BCS_Hedge_CE_OI": null,
    "BCS_Spread_Width": null,
    "BCS_Net_Premium": null,
    "BCS_Max_Profit": null,
    "BCS_Max_Loss": null,
    "BCS_Breakeven": null,
    "BCS_Risk_Reward": null,
    "Status": "Momentum Lost",
    "Sell_Alert_Sent": false,
    "Breakdown_Date": "2026-06-02",
    "Sell_Zone_EMA_Confirmed": true,
    "Sell_Zone_EMA_Confirm_Date": "2026-05-18",
    "Scanned_At": "2026-06-03 13:04:12"
  },
  {
    "Ticker": "TRENT",
    "Today_Close": 4252.6,
    "Surge_High": 3999.0,
    "Yesterday_High": 4335.7,
    "Yesterday_Close": 4224.0,
    "Yesterday_Low": 4190.0,
    "Drop_Pct": 0.78,
    "Breakdown_Volume": 652098,
    "Avg_Volume_20d": 673234,
    "Volume_Ratio": 0.97,
    "EMA_At_Detection": 4199.55,
    "EMA_Breached_At_Detection": true,
    "Below_EMA": true,
    "Surge_Gain_Pct": 18.48,
    "Surge_Candles": 4,
    "Surge_Allowed_Reds": 2,
    "Surge_Start": "2026-03-30",
    "Surge_End": "2026-04-08",
    "Days_Since_Surge_End": 56,
    "Prev_Pullup_High": 4498.0,
    "Lifetime_52W_High": 5248.0,
    "Suggested_Strike": 4000.0,
    "Expiry": "30-Jun-2026",
    "CE_LTP": 300.9,
    "CE_OI": 243,
    "IV_Pct": 26.6,
    "CE_30d_High": 327.85,
    "CE_Above_30d_High": false,
    "Remark": "CE Below 30d High",
    "NSE_Hist_Calls": 1,
    "BCS_Hedge_Strike": 4200.0,
    "BCS_Hedge_CE_LTP": 166.0,
    "BCS_Hedge_CE_OI": 2661,
    "BCS_Spread_Width": 200.0,
    "BCS_Net_Premium": 134.9,
    "BCS_Max_Profit": 134.9,
    "BCS_Max_Loss": 65.1,
    "BCS_Breakeven": 4134.9,
    "BCS_Risk_Reward": 0.48,
    "Status": "Momentum Lost",
    "Sell_Alert_Sent": false,
    "Breakdown_Date": "2026-06-01",
    "Sell_Zone_EMA_Confirmed": true,
    "Sell_Zone_EMA_Confirm_Date": "2026-06-01",
    "Scanned_At": "2026-06-03 13:04:33"
  },
  {
    "Ticker": "TIINDIA",
    "Today_Close": 3057.0,
    "Surge_High": 3153.0,
    "Yesterday_High": 3250.0,
    "Yesterday_Close": 3141.4,
    "Yesterday_Low": 3121.9,
    "Drop_Pct": 2.09,
    "Breakdown_Volume": 335850,
    "Avg_Volume_20d": 377695,
    "Volume_Ratio": 0.89,
    "EMA_At_Detection": 3074.23,
    "EMA_Breached_At_Detection": true,
    "Below_EMA": true,
    "Surge_Gain_Pct": 22.62,
    "Surge_Candles": 12,
    "Surge_Allowed_Reds": 4,
    "Surge_Start": "2026-03-30",
    "Surge_End": "2026-04-23",
    "Days_Since_Surge_End": 41,
    "Prev_Pullup_High": 3153.0,
    "Lifetime_52W_High": 3417.01,
    "Suggested_Strike": 3200.0,
    "Expiry": "30-Jun-2026",
    "CE_LTP": 77.55,
    "CE_OI": 329,
    "IV_Pct": 38.9,
    "CE_30d_High": 151.0,
    "CE_Above_30d_High": false,
    "Remark": "CE Below 30d High",
    "NSE_Hist_Calls": 1,
    "BCS_Hedge_Strike": 3400.0,
    "BCS_Hedge_CE_LTP": 29.05,
    "BCS_Hedge_CE_OI": 233,
    "BCS_Spread_Width": 200.0,
    "BCS_Net_Premium": 48.5,
    "BCS_Max_Profit": 48.5,
    "BCS_Max_Loss": 151.5,
    "BCS_Breakeven": 3248.5,
    "BCS_Risk_Reward": 3.12,
    "Status": "Momentum Lost",
    "Sell_Alert_Sent": false,
    "Breakdown_Date": "2026-06-01",
    "Sell_Zone_EMA_Confirmed": true,
    "Sell_Zone_EMA_Confirm_Date": "2026-05-14",
    "Scanned_At": "2026-06-03 13:04:47"
  },
  {
    "Ticker": "VBL",
    "Today_Close": 531.3,
    "Surge_High": 534.19,
    "Yesterday_High": 513.7,
    "Yesterday_Close": 513.7,
    "Yesterday_Low": 513.7,
    "Drop_Pct": 1.35,
    "Breakdown_Volume": 5234719,
    "Avg_Volume_20d": 8943852,
    "Volume_Ratio": 0.59,
    "EMA_At_Detection": 502.44,
    "EMA_Breached_At_Detection": true,
    "Below_EMA": false,
    "Surge_Gain_Pct": 29.02,
    "Surge_Candles": 12,
    "Surge_Allowed_Reds": 3,
    "Surge_Start": "2026-03-30",
    "Surge_End": "2026-04-22",
    "Days_Since_Surge_End": 34,
    "Prev_Pullup_High": 534.19,
    "Lifetime_52W_High": 543.95,
    "Suggested_Strike": 550,
    "Expiry": "30-Jun-2026",
    "CE_LTP": 39.5,
    "CE_OI": 1107,
    "IV_Pct": 26.9,
    "CE_30d_High": 46.9,
    "CE_Above_30d_High": false,
    "Remark": "CE Below 30d High",
    "NSE_Hist_Calls": 1,
    "BCS_Hedge_Strike": 550.0,
    "BCS_Hedge_CE_LTP": 11.45,
    "BCS_Hedge_CE_OI": 473,
    "BCS_Spread_Width": 50.0,
    "BCS_Net_Premium": 28.05,
    "BCS_Max_Profit": 28.05,
    "BCS_Max_Loss": 21.95,
    "BCS_Breakeven": 528.05,
    "BCS_Risk_Reward": 0.78,
    "Status": "Momentum Lost",
    "Sell_Alert_Sent": false,
    "Breakdown_Date": "2026-05-04",
    "Sell_Zone_EMA_Confirmed": true,
    "Sell_Zone_EMA_Confirm_Date": "2026-05-12",
    "Scanned_At": "2026-05-26 17:01:08"
  },
  {
    "Ticker": "VOLTAS",
    "Today_Close": 1221.0,
    "Surge_High": 1503.5,
    "Yesterday_High": 1300.0,
    "Yesterday_Close": 1245.7,
    "Yesterday_Low": 1232.2,
    "Drop_Pct": 0.31,
    "Breakdown_Volume": 766252,
    "Avg_Volume_20d": 1128505,
    "Volume_Ratio": 0.68,
    "EMA_At_Detection": 1261.65,
    "EMA_Breached_At_Detection": true,
    "Below_EMA": true,
    "Surge_Gain_Pct": 21.42,
    "Surge_Candles": 8,
    "Surge_Allowed_Reds": 3,
    "Surge_Start": "2026-04-07",
    "Surge_End": "2026-04-22",
    "Days_Since_Surge_End": 42,
    "Prev_Pullup_High": 1582.5,
    "Lifetime_52W_High": 1582.5,
    "Suggested_Strike": 1600.0,
    "Expiry": "30-Jun-2026",
    "CE_LTP": 0.7,
    "CE_OI": 293,
    "IV_Pct": 43.4,
    "CE_30d_High": 29.0,
    "CE_Above_30d_High": false,
    "Remark": "CE Below 30d High",
    "NSE_Hist_Calls": 1,
    "BCS_Hedge_Strike": null,
    "BCS_Hedge_CE_LTP": null,
    "BCS_Hedge_CE_OI": null,
    "BCS_Spread_Width": null,
    "BCS_Net_Premium": null,
    "BCS_Max_Profit": null,
    "BCS_Max_Loss": null,
    "BCS_Breakeven": null,
    "BCS_Risk_Reward": null,
    "Status": "Momentum Lost",
    "Sell_Alert_Sent": false,
    "Breakdown_Date": "2026-06-01",
    "Sell_Zone_EMA_Confirmed": true,
    "Sell_Zone_EMA_Confirm_Date": "2026-05-26",
    "Scanned_At": "2026-06-03 13:05:18"
  },
  {
    "Ticker": "RVNL",
    "Today_Close": 234.3,
    "Surge_High": 311.85,
    "Yesterday_High": 255.2,
    "Yesterday_Close": 245.45,
    "Yesterday_Low": 243.0,
    "Drop_Pct": 0.59,
    "Breakdown_Volume": 9432010,
    "Avg_Volume_20d": 9506552,
    "Volume_Ratio": 0.99,
    "EMA_At_Detection": 257.73,
    "EMA_Breached_At_Detection": true,
    "Below_EMA": true,
    "Surge_Gain_Pct": 21.39,
    "Surge_Candles": 8,
    "Surge_Allowed_Reds": 4,
    "Surge_Start": "2026-03-30",
    "Surge_End": "2026-04-17",
    "Days_Since_Surge_End": 47,
    "Prev_Pullup_High": 337.94,
    "Lifetime_52W_High": 399.45,
    "Suggested_Strike": 320.0,
    "Expiry": "30-Jun-2026",
    "CE_LTP": 0.32,
    "CE_OI": 462,
    "IV_Pct": 55.5,
    "CE_30d_High": 12.66,
    "CE_Above_30d_High": false,
    "Remark": "CE Below 30d High",
    "NSE_Hist_Calls": 1,
    "BCS_Hedge_Strike": 340.0,
    "BCS_Hedge_CE_LTP": 0.21,
    "BCS_Hedge_CE_OI": 101,
    "BCS_Spread_Width": 20.0,
    "BCS_Net_Premium": 0.11,
    "BCS_Max_Profit": 0.11,
    "BCS_Max_Loss": 19.89,
    "BCS_Breakeven": 320.11,
    "BCS_Risk_Reward": 180.82,
    "Status": "Momentum Lost",
    "Sell_Alert_Sent": false,
    "Breakdown_Date": "2026-06-01",
    "Sell_Zone_EMA_Confirmed": true,
    "Sell_Zone_EMA_Confirm_Date": "2026-05-26",
    "Scanned_At": "2026-06-03 13:05:32"
  },
  {
    "Ticker": "ANGELONE",
    "Today_Close": 331.3,
    "Surge_High": 351.0,
    "Yesterday_High": 344.75,
    "Yesterday_Close": 342.65,
    "Yesterday_Low": 331.9,
    "Drop_Pct": 0.18,
    "Breakdown_Volume": 4158318,
    "Avg_Volume_20d": 8129399,
    "Volume_Ratio": 0.51,
    "EMA_At_Detection": 335.11,
    "EMA_Breached_At_Detection": true,
    "Below_EMA": true,
    "Surge_Gain_Pct": 44.42,
    "Surge_Candles": 11,
    "Surge_Allowed_Reds": 4,
    "Surge_Start": "2026-03-30",
    "Surge_End": "2026-04-22",
    "Days_Since_Surge_End": 42,
    "Prev_Pullup_High": 334.95,
    "Lifetime_52W_High": 351.0,
    "Suggested_Strike": 360,
    "Expiry": "30-Jun-2026",
    "CE_LTP": 14.1,
    "CE_OI": 146,
    "IV_Pct": 42.0,
    "CE_30d_High": 26.0,
    "CE_Above_30d_High": false,
    "Remark": "CE Below 30d High",
    "NSE_Hist_Calls": 1,
    "BCS_Hedge_Strike": 355.0,
    "BCS_Hedge_CE_LTP": 7.0,
    "BCS_Hedge_CE_OI": 269,
    "BCS_Spread_Width": 20.0,
    "BCS_Net_Premium": 7.1,
    "BCS_Max_Profit": 7.1,
    "BCS_Max_Loss": 12.9,
    "BCS_Breakeven": 342.1,
    "BCS_Risk_Reward": 1.82,
    "Status": "Momentum Lost",
    "Sell_Alert_Sent": false,
    "Breakdown_Date": "2026-06-03",
    "Sell_Zone_EMA_Confirmed": true,
    "Sell_Zone_EMA_Confirm_Date": "2026-06-03",
    "Scanned_At": "2026-06-03 12:52:00"
  },
  {
    "Ticker": "BSE",
    "Today_Close": 3883.9,
    "Surge_High": 4446.8,
    "Yesterday_High": 4198.0,
    "Yesterday_Close": 4066.6,
    "Yesterday_Low": 4031.9,
    "Drop_Pct": 2.48,
    "Breakdown_Volume": 5568609,
    "Avg_Volume_20d": 4248111,
    "Volume_Ratio": 1.31,
    "EMA_At_Detection": 4122.17,
    "EMA_Breached_At_Detection": true,
    "Below_EMA": true,
    "Surge_Gain_Pct": 31.6,
    "Surge_Candles": 9,
    "Surge_Allowed_Reds": 3,
    "Surge_Start": "2026-03-30",
    "Surge_End": "2026-04-17",
    "Days_Since_Surge_End": 47,
    "Prev_Pullup_High": 3994.0,
    "Lifetime_52W_High": 4446.8,
    "Suggested_Strike": 4600,
    "Expiry": "30-Jun-2026",
    "CE_LTP": 365.0,
    "CE_OI": 153,
    "IV_Pct": 43.2,
    "CE_30d_High": 804.45,
    "CE_Above_30d_High": false,
    "Remark": "CE Below 30d High",
    "NSE_Hist_Calls": 1,
    "BCS_Hedge_Strike": 3800.0,
    "BCS_Hedge_CE_LTP": 213.35,
    "BCS_Hedge_CE_OI": 412,
    "BCS_Spread_Width": 200.0,
    "BCS_Net_Premium": 151.65,
    "BCS_Max_Profit": 151.65,
    "BCS_Max_Loss": 48.35,
    "BCS_Breakeven": 3751.65,
    "BCS_Risk_Reward": 0.32,
    "Status": "Momentum Lost",
    "Sell_Alert_Sent": false,
    "Breakdown_Date": "2026-06-02",
    "Sell_Zone_EMA_Confirmed": true,
    "Sell_Zone_EMA_Confirm_Date": "2026-06-02",
    "Scanned_At": "2026-06-03 12:53:02"
  },
  {
    "Ticker": "BHEL",
    "Today_Close": 402.95,
    "Surge_High": 424.9,
    "Yesterday_High": 422.35,
    "Yesterday_Close": 422.35,
    "Yesterday_Low": 422.35,
    "Drop_Pct": 1.33,
    "Breakdown_Volume": 18794737,
    "Avg_Volume_20d": 19545649,
    "Volume_Ratio": 0.96,
    "EMA_At_Detection": 413.77,
    "EMA_Breached_At_Detection": true,
    "Below_EMA": false,
    "Surge_Gain_Pct": 44.4,
    "Surge_Candles": 14,
    "Surge_Allowed_Reds": 2,
    "Surge_Start": "2026-04-06",
    "Surge_End": "2026-04-28",
    "Days_Since_Surge_End": 36,
    "Prev_Pullup_High": 408.9,
    "Lifetime_52W_High": 424.9,
    "Suggested_Strike": 440,
    "Expiry": "30-Jun-2026",
    "CE_LTP": 35.65,
    "CE_OI": 39,
    "IV_Pct": 23.8,
    "CE_30d_High": 57.2,
    "CE_Above_30d_High": false,
    "Remark": "CE Below 30d High",
    "NSE_Hist_Calls": 1,
    "BCS_Hedge_Strike": 390.0,
    "BCS_Hedge_CE_LTP": 24.6,
    "BCS_Hedge_CE_OI": 318,
    "BCS_Spread_Width": 20.0,
    "BCS_Net_Premium": 11.05,
    "BCS_Max_Profit": 11.05,
    "BCS_Max_Loss": 8.95,
    "BCS_Breakeven": 381.05,
    "BCS_Risk_Reward": 0.81,
    "Status": "Momentum Lost",
    "Sell_Alert_Sent": false,
    "Breakdown_Date": "2026-05-29",
    "Sell_Zone_EMA_Confirmed": true,
    "Sell_Zone_EMA_Confirm_Date": "2026-06-01",
    "Scanned_At": "2026-06-03 12:53:38"
  },
  {
    "Ticker": "BIOCON",
    "Today_Close": 412.6,
    "Surge_High": 440.4,
    "Yesterday_High": 435.0,
    "Yesterday_Close": 425.65,
    "Yesterday_Low": 424.5,
    "Drop_Pct": 1.81,
    "Breakdown_Volume": 3030795,
    "Avg_Volume_20d": 5776726,
    "Volume_Ratio": 0.52,
    "EMA_At_Detection": 424.76,
    "EMA_Breached_At_Detection": true,
    "Below_EMA": true,
    "Surge_Gain_Pct": 21.27,
    "Surge_Candles": 12,
    "Surge_Allowed_Reds": 6,
    "Surge_Start": "2026-05-01",
    "Surge_End": "2026-05-26",
    "Days_Since_Surge_End": 8,
    "Prev_Pullup_High": 420.25,
    "Lifetime_52W_High": 440.4,
    "Suggested_Strike": 450.0,
    "Expiry": "30-Jun-2026",
    "CE_LTP": 3.15,
    "CE_OI": 866,
    "IV_Pct": 30.9,
    "CE_30d_High": 12.25,
    "CE_Above_30d_High": false,
    "Remark": "CE Below 30d High",
    "NSE_Hist_Calls": 1,
    "BCS_Hedge_Strike": 470.0,
    "BCS_Hedge_CE_LTP": 1.35,
    "BCS_Hedge_CE_OI": 219,
    "BCS_Spread_Width": 20.0,
    "BCS_Net_Premium": 1.8,
    "BCS_Max_Profit": 1.8,
    "BCS_Max_Loss": 18.2,
    "BCS_Breakeven": 451.8,
    "BCS_Risk_Reward": 10.11,
    "Status": "Momentum Lost",
    "Sell_Alert_Sent": false,
    "Breakdown_Date": "2026-06-02",
    "Sell_Zone_EMA_Confirmed": true,
    "Sell_Zone_EMA_Confirm_Date": "2026-06-02",
    "Scanned_At": "2026-06-03 12:53:56"
  },
  {
    "Ticker": "JSWENERGY",
    "Today_Close": 576.35,
    "Surge_High": 608.9,
    "Yesterday_High": 617.35,
    "Yesterday_Close": 595.05,
    "Yesterday_Low": 592.1,
    "Drop_Pct": 1.46,
    "Breakdown_Volume": 2465291,
    "Avg_Volume_20d": 4511096,
    "Volume_Ratio": 0.55,
    "EMA_At_Detection": 575.78,
    "EMA_Breached_At_Detection": true,
    "Below_EMA": false,
    "Surge_Gain_Pct": 18.23,
    "Surge_Candles": 6,
    "Surge_Allowed_Reds": 6,
    "Surge_Start": "2026-05-13",
    "Surge_End": "2026-05-28",
    "Days_Since_Surge_End": 6,
    "Prev_Pullup_High": 585.65,
    "Lifetime_52W_High": 617.35,
    "Suggested_Strike": 610.0,
    "Expiry": "30-Jun-2026",
    "CE_LTP": 9.8,
    "CE_OI": 612,
    "IV_Pct": 34.0,
    "CE_30d_High": 19.65,
    "CE_Above_30d_High": false,
    "Remark": "CE Below 30d High",
    "NSE_Hist_Calls": 1,
    "BCS_Hedge_Strike": 660.0,
    "BCS_Hedge_CE_LTP": 3.0,
    "BCS_Hedge_CE_OI": 363,
    "BCS_Spread_Width": 50.0,
    "BCS_Net_Premium": 6.8,
    "BCS_Max_Profit": 6.8,
    "BCS_Max_Loss": 43.2,
    "BCS_Breakeven": 616.8,
    "BCS_Risk_Reward": 6.35,
    "Status": "Momentum Lost",
    "Sell_Alert_Sent": false,
    "Breakdown_Date": "2026-06-01",
    "Sell_Zone_EMA_Confirmed": false,
    "Sell_Zone_EMA_Confirm_Date": null,
    "Scanned_At": "2026-06-03 12:58:47"
  },
  {
    "Ticker": "MCX",
    "Today_Close": 2831.2,
    "Surge_High": 3480.0,
    "Yesterday_High": 3177.0,
    "Yesterday_Close": 2954.5,
    "Yesterday_Low": 2906.2,
    "Drop_Pct": 0.54,
    "Breakdown_Volume": 3492170,
    "Avg_Volume_20d": 3669163,
    "Volume_Ratio": 0.95,
    "EMA_At_Detection": 3129.65,
    "EMA_Breached_At_Detection": true,
    "Below_EMA": true,
    "Surge_Gain_Pct": 19.79,
    "Surge_Candles": 8,
    "Surge_Allowed_Reds": 3,
    "Surge_Start": "2026-03-30",
    "Surge_End": "2026-04-16",
    "Days_Since_Surge_End": 48,
    "Prev_Pullup_High": 3265.0,
    "Lifetime_52W_High": 3480.0,
    "Suggested_Strike": 3600,
    "Expiry": "30-Jun-2026",
    "CE_LTP": 81.05,
    "CE_OI": 466,
    "IV_Pct": 40.5,
    "CE_30d_High": 280.15,
    "CE_Above_30d_High": false,
    "Remark": "CE Below 30d High",
    "NSE_Hist_Calls": 1,
    "BCS_Hedge_Strike": 3150.0,
    "BCS_Hedge_CE_LTP": 34.15,
    "BCS_Hedge_CE_OI": 428,
    "BCS_Spread_Width": 200.0,
    "BCS_Net_Premium": 46.9,
    "BCS_Max_Profit": 46.9,
    "BCS_Max_Loss": 153.1,
    "BCS_Breakeven": 2996.9,
    "BCS_Risk_Reward": 3.26,
    "Status": "Momentum Lost",
    "Sell_Alert_Sent": false,
    "Breakdown_Date": "2026-06-01",
    "Sell_Zone_EMA_Confirmed": true,
    "Sell_Zone_EMA_Confirm_Date": "2026-06-01",
    "Scanned_At": "2026-06-03 13:00:50"
  }
]