{"config":{"lookback_days":252,"min_gain_percent":18,"min_green_candles":2,"surge_recency_days":45,"min_drop_percent":0.1,"min_breakdown_volume_ratio":0.5,"ema_period":9,"price_proximity_percent":1,"sell_zone_lookback_days":10,"expiry_mode":"auto","min_days_to_expiry":5,"premium_vol_surge_threshold":1.5},"years_tested":10,"aggregate":{"tickers":["HDFCAMC"],"total_trades":8,"wins":5,"losses":3,"accuracy_pct":62.5,"total_pnl":5.16,"avg_pnl":0.64,"premium_analysis":{"threshold":1.5,"high_vol_cohort":{"trades":3,"wins":2,"losses":1,"accuracy_pct":66.7,"avg_premium":7.0,"avg_pnl":-1.33,"avg_prem_score":22.24},"normal_cohort":{"trades":5,"wins":3,"losses":2,"accuracy_pct":60.0,"avg_premium":15.43,"avg_pnl":1.83,"avg_prem_score":17.83}},"dual_expiry_comparison":{"current_month":{"trades":8,"wins":5,"losses":3,"accuracy_pct":62.5,"avg_premium":9.65,"avg_pnl":2.97,"total_pnl":23.75},"next_month":{"trades":8,"wins":4,"losses":4,"accuracy_pct":50.0,"avg_premium":34.7,"avg_pnl":-12.28,"total_pnl":-98.26}}},"per_ticker":[{"ticker":"HDFCAMC","summary":{"total_trades":8,"wins":5,"losses":3,"accuracy_pct":62.5,"avg_pnl_per_unit":0.65,"avg_premium":12.27,"total_pnl":5.16,"premium_analysis":{"threshold":1.5,"high_vol_cohort":{"trades":3,"wins":2,"losses":1,"accuracy_pct":66.7,"avg_premium":7.0,"avg_pnl":-1.33,"avg_prem_score":22.24},"normal_cohort":{"trades":5,"wins":3,"losses":2,"accuracy_pct":60.0,"avg_premium":15.43,"avg_pnl":1.83,"avg_prem_score":17.83}},"dual_expiry_comparison":{"current_month":{"trades":8,"wins":5,"losses":3,"accuracy_pct":62.5,"avg_premium":9.65,"avg_pnl":2.97,"total_pnl":23.75},"next_month":{"trades":8,"wins":4,"losses":4,"accuracy_pct":50.0,"avg_premium":34.7,"avg_pnl":-12.28,"total_pnl":-98.26}}},"trades":[{"entry_date":"2019-06-24","expiry_date":"2019-07-25","actual_data_date":"2019-07-25","entry_price":966.92,"surge_high":978.0,"strike":1000,"entry_ce_premium":22.48,"expiry_close":1045.57,"intrinsic_value":45.57,"iv_sigma":30.3,"T_days":31,"expiry_mode":"auto","expiry_label":"auto","result":"LOSS","pnl_per_unit":-23.09,"return_pct":-102.7,"vol_at_g3":550336,"avg_vol_20d_g3":405788,"vol_surge_at_g3":1.36,"premium_score":30.57,"is_high_prem":false,"ticker":"HDFCAMC","gate1_date":"2019-06-18","gate2_date":"2019-06-18","gate3_date":"2019-06-24","surge_gain_pct":22.3,"surge_candles":17,"volume_ratio":7.05,"cur_expiry":{"expiry_date":"2019-06-27","actual_data_date":"2019-06-27","T_days":3,"entry_ce_premium":1.5,"expiry_close":1018.33,"intrinsic_value":18.33,"result":"LOSS","pnl_per_unit":-4.5,"return_pct":-300.0},"nxt_expiry":{"expiry_date":"2019-07-25","actual_data_date":"2019-07-25","T_days":31,"entry_ce_premium":22.48,"expiry_close":1045.57,"intrinsic_value":45.57,"result":"LOSS","pnl_per_unit":-23.09,"return_pct":-102.7}},{"entry_date":"2019-07-17","expiry_date":"2019-07-25","actual_data_date":"2019-07-25","entry_price":1037.7,"surge_high":1049.5,"strike":1100,"entry_ce_premium":4.07,"expiry_close":1045.57,"intrinsic_value":0.0,"iv_sigma":35.8,"T_days":8,"expiry_mode":"auto","expiry_label":"auto","result":"WIN","pnl_per_unit":4.07,"return_pct":100.0,"vol_at_g3":2329750,"avg_vol_20d_g3":521834,"vol_surge_at_g3":4.46,"premium_score":18.15,"is_high_prem":true,"ticker":"HDFCAMC","gate1_date":"2019-07-02","gate2_date":"2019-07-08","gate3_date":"2019-07-17","surge_gain_pct":22.3,"surge_candles":17,"volume_ratio":1.06,"cur_expiry":{"expiry_date":"2019-07-25","actual_data_date":"2019-07-25","T_days":8,"entry_ce_premium":4.07,"expiry_close":1045.57,"intrinsic_value":0.0,"result":"WIN","pnl_per_unit":4.07,"return_pct":100.0},"nxt_expiry":{"expiry_date":"2019-08-29","actual_data_date":"2019-08-29","T_days":43,"entry_ce_premium":29.5,"expiry_close":1216.25,"intrinsic_value":116.25,"result":"LOSS","pnl_per_unit":-86.75,"return_pct":-294.1}},{"entry_date":"2024-02-15","expiry_date":"2024-02-29","actual_data_date":"2024-02-29","entry_price":1891.5,"surge_high":1922.0,"strike":2000,"entry_ce_premium":7.62,"expiry_close":1876.5,"intrinsic_value":0.0,"iv_sigma":26.1,"T_days":14,"expiry_mode":"auto","expiry_label":"auto","result":"WIN","pnl_per_unit":7.62,"return_pct":100.0,"vol_at_g3":634966,"avg_vol_20d_g3":954917,"vol_surge_at_g3":0.66,"premium_score":5.03,"is_high_prem":false,"ticker":"HDFCAMC","gate1_date":"2019-11-15","gate2_date":"2019-11-29","gate3_date":"2024-02-15","surge_gain_pct":22.84,"surge_candles":4,"volume_ratio":1.16,"cur_expiry":{"expiry_date":"2024-02-29","actual_data_date":"2024-02-29","T_days":14,"entry_ce_premium":7.62,"expiry_close":1876.5,"intrinsic_value":0.0,"result":"WIN","pnl_per_unit":7.62,"return_pct":100.0},"nxt_expiry":{"expiry_date":"2024-03-28","actual_data_date":"2024-03-28","T_days":42,"entry_ce_premium":31.56,"expiry_close":1877.05,"intrinsic_value":0.0,"result":"WIN","pnl_per_unit":31.56,"return_pct":100.0}},{"entry_date":"2024-01-09","expiry_date":"2024-01-25","actual_data_date":"2024-01-25","entry_price":1707.62,"surge_high":1723.3,"strike":1800,"entry_ce_premium":3.78,"expiry_close":1714.32,"intrinsic_value":0.0,"iv_sigma":19.4,"T_days":16,"expiry_mode":"auto","expiry_label":"auto","result":"WIN","pnl_per_unit":3.78,"return_pct":100.0,"vol_at_g3":932218,"avg_vol_20d_g3":909270,"vol_surge_at_g3":1.03,"premium_score":3.89,"is_high_prem":false,"ticker":"HDFCAMC","gate1_date":"2020-04-21","gate2_date":"2020-04-24","gate3_date":"2024-01-09","surge_gain_pct":36.3,"surge_candles":8,"volume_ratio":0.83,"cur_expiry":{"expiry_date":"2024-01-25","actual_data_date":"2024-01-25","T_days":16,"entry_ce_premium":3.78,"expiry_close":1714.32,"intrinsic_value":0.0,"result":"WIN","pnl_per_unit":3.78,"return_pct":100.0},"nxt_expiry":{"expiry_date":"2024-02-29","actual_data_date":"2024-02-29","T_days":51,"entry_ce_premium":21.31,"expiry_close":1876.5,"intrinsic_value":76.5,"result":"LOSS","pnl_per_unit":-55.19,"return_pct":-259.0}},{"entry_date":"2021-01-11","expiry_date":"2021-01-28","actual_data_date":"2021-01-28","entry_price":1591.22,"surge_high":1610.0,"strike":1700,"entry_ce_premium":7.32,"expiry_close":1460.43,"intrinsic_value":0.0,"iv_sigma":27.7,"T_days":17,"expiry_mode":"auto","expiry_label":"auto","result":"WIN","pnl_per_unit":7.32,"return_pct":100.0,"vol_at_g3":677092,"avg_vol_20d_g3":807568,"vol_surge_at_g3":0.84,"premium_score":6.15,"is_high_prem":false,"ticker":"HDFCAMC","gate1_date":"2020-05-11","gate2_date":"2020-05-11","gate3_date":"2021-01-11","surge_gain_pct":36.3,"surge_candles":8,"volume_ratio":1.02,"cur_expiry":{"expiry_date":"2021-01-28","actual_data_date":"2021-01-28","T_days":17,"entry_ce_premium":7.32,"expiry_close":1460.43,"intrinsic_value":0.0,"result":"WIN","pnl_per_unit":7.32,"return_pct":100.0},"nxt_expiry":{"expiry_date":"2021-02-25","actual_data_date":"2021-02-25","T_days":45,"entry_ce_premium":26.89,"expiry_close":1475.97,"intrinsic_value":0.0,"result":"WIN","pnl_per_unit":26.89,"return_pct":100.0}},{"entry_date":"2021-09-09","expiry_date":"2021-09-30","actual_data_date":"2021-09-30","entry_price":1624.2,"surge_high":1679.45,"strike":1700,"entry_ce_premium":7.91,"expiry_close":1454.3,"intrinsic_value":0.0,"iv_sigma":19.5,"T_days":21,"expiry_mode":"auto","expiry_label":"auto","result":"WIN","pnl_per_unit":7.91,"return_pct":100.0,"vol_at_g3":2528166,"avg_vol_20d_g3":636423,"vol_surge_at_g3":3.97,"premium_score":31.4,"is_high_prem":true,"ticker":"HDFCAMC","gate1_date":"2021-01-18","gate2_date":"2021-01-21","gate3_date":"2021-09-09","surge_gain_pct":19.02,"surge_candles":11,"volume_ratio":0.76,"cur_expiry":{"expiry_date":"2021-09-30","actual_data_date":"2021-09-30","T_days":21,"entry_ce_premium":7.91,"expiry_close":1454.3,"intrinsic_value":0.0,"result":"WIN","pnl_per_unit":7.91,"return_pct":100.0},"nxt_expiry":{"expiry_date":"2021-10-28","actual_data_date":"2021-10-28","T_days":49,"entry_ce_premium":22.89,"expiry_close":1314.72,"intrinsic_value":0.0,"result":"WIN","pnl_per_unit":22.89,"return_pct":100.0}},{"entry_date":"2025-05-14","expiry_date":"2025-05-29","actual_data_date":"2025-05-29","entry_price":2284.45,"surge_high":2312.5,"strike":2400,"entry_ce_premium":35.97,"expiry_close":2422.45,"intrinsic_value":22.45,"iv_sigma":41.7,"T_days":15,"expiry_mode":"auto","expiry_label":"auto","result":"LOSS","pnl_per_unit":13.52,"return_pct":37.6,"vol_at_g3":1213162,"avg_vol_20d_g3":1004020,"vol_surge_at_g3":1.21,"premium_score":43.52,"is_high_prem":false,"ticker":"HDFCAMC","gate1_date":"2025-04-25","gate2_date":"2025-05-06","gate3_date":"2025-05-14","surge_gain_pct":22.17,"surge_candles":8,"volume_ratio":1.25,"cur_expiry":{"expiry_date":"2025-05-29","actual_data_date":"2025-05-29","T_days":15,"entry_ce_premium":35.97,"expiry_close":2422.45,"intrinsic_value":22.45,"result":"LOSS","pnl_per_unit":13.52,"return_pct":37.6},"nxt_expiry":{"expiry_date":"2025-06-26","actual_data_date":"2025-06-26","T_days":43,"entry_ce_premium":90.03,"expiry_close":2537.5,"intrinsic_value":137.5,"result":"LOSS","pnl_per_unit":-47.47,"return_pct":-52.7}},{"entry_date":"2025-07-10","expiry_date":"2025-07-31","actual_data_date":"2025-07-31","entry_price":2603.75,"surge_high":2639.45,"strike":2800,"entry_ce_premium":9.03,"expiry_close":2825.0,"intrinsic_value":25.0,"iv_sigma":24.2,"T_days":21,"expiry_mode":"auto","expiry_label":"auto","result":"LOSS","pnl_per_unit":-15.97,"return_pct":-176.9,"vol_at_g3":1330220,"avg_vol_20d_g3":701562,"vol_surge_at_g3":1.9,"premium_score":17.16,"is_high_prem":true,"ticker":"HDFCAMC","gate1_date":"2025-06-13","gate2_date":"2025-06-13","gate3_date":"2025-07-10","surge_gain_pct":22.17,"surge_candles":8,"volume_ratio":0.86,"cur_expiry":{"expiry_date":"2025-07-31","actual_data_date":"2025-07-31","T_days":21,"entry_ce_premium":9.03,"expiry_close":2825.0,"intrinsic_value":25.0,"result":"LOSS","pnl_per_unit":-15.97,"return_pct":-176.9},"nxt_expiry":{"expiry_date":"2025-08-28","actual_data_date":"2025-08-28","T_days":49,"entry_ce_premium":32.9,"expiry_close":2791.0,"intrinsic_value":0.0,"result":"WIN","pnl_per_unit":32.9,"return_pct":100.0}}]}],"from_cache":false,"cached_at":"2026-05-26 10:58:16 IST"}